[{"id":"ChwKGkNPV2FxYVRjMDRZREZXckR3Z1FkY2VvSkZB","videoId":"gFBabc31RaU","userId":"UCV7pAnoqiqRSEUq7wAt_pnA","timestamp":1718114769865,"videoOffsetTimeMsec":"286347","jsonMessage":"{\"runs\":[{\"text\":\"早安~\",\"bold\":false,\"italics\":false,\"strikethrough\":false}],\"text\":\"早安~\"}"},{"id":"ChwKGkNPUE5zT3JyMDRZREZWVFF3Z1FkTmZZQ2tB","videoId":"gFBabc31RaU","userId":"UCV7pAnoqiqRSEUq7wAt_pnA","timestamp":1718118943316,"videoOffsetTimeMsec":"4459789","jsonMessage":"{\"runs\":[{\"text\":\"安安~\",\"bold\":false,\"italics\":false,\"strikethrough\":false}],\"text\":\"安安~\"}"},{"id":"ChwKGkNMNkN2YlRzMDRZREZiX0h3Z1FkZS1vRnJ3","videoId":"gFBabc31RaU","userId":"UCV7pAnoqiqRSEUq7wAt_pnA","timestamp":1718119098713,"videoOffsetTimeMsec":"4615215","jsonMessage":"{\"runs\":[{\"text\":\"聲音可愛\",\"bold\":false,\"italics\":false,\"strikethrough\":false}],\"text\":\"聲音可愛\"}"},{"id":"ChwKGkNLbUh1cUh4MDRZREZWWEx3Z1FkMWJRSUFR","videoId":"gFBabc31RaU","userId":"UCV7pAnoqiqRSEUq7wAt_pnA","timestamp":1718120400992,"videoOffsetTimeMsec":"5916479","jsonMessage":"{\"runs\":[{\"text\":\"你可以自己換\",\"bold\":false,\"italics\":false,\"strikethrough\":false}],\"text\":\"你可以自己換\"}"},{"id":"ChwKGkNMRElpZW5maUljREZkWEN3Z1FkVEJRSmtR","videoId":"dfhI39U64yM","userId":"UCV7pAnoqiqRSEUq7wAt_pnA","timestamp":1719936785490,"videoOffsetTimeMsec":"7959964","jsonMessage":"{\"runs\":[{\"text\":\"安安~\",\"bold\":false,\"italics\":false,\"strikethrough\":false}],\"text\":\"安安~\"}"},{"id":"ChwKGkNMYmtvY0xnaUljREZkWEN3Z1FkVEJRSmtR","videoId":"dfhI39U64yM","userId":"UCV7pAnoqiqRSEUq7wAt_pnA","timestamp":1719936972536,"videoOffsetTimeMsec":"8146908","jsonMessage":"{\"runs\":[{\"text\":\"庫庫88~\",\"bold\":false,\"italics\":false,\"strikethrough\":false}],\"text\":\"庫庫88~\"}"},{"id":"ChwKGkNPN3Z0Y3JnaUljREZXSV9yUVlkNGdRQ1Vn","videoId":"dfhI39U64yM","userId":"UCV7pAnoqiqRSEUq7wAt_pnA","timestamp":1719936989641,"videoOffsetTimeMsec":"8164059","jsonMessage":"{\"runs\":[{\"text\":\"晚安~\",\"bold\":false,\"italics\":false,\"strikethrough\":false}],\"text\":\"晚安~\"}"},{"id":"ChwKGkNOT0M0LUhnaUljREZaTEh3Z1FkM1hRT0l3","videoId":"dfhI39U64yM","userId":"UCV7pAnoqiqRSEUq7wAt_pnA","timestamp":1719937038614,"videoOffsetTimeMsec":"8212937","jsonMessage":"{\"runs\":[{\"text\":\"888888888888888\",\"bold\":false,\"italics\":false,\"strikethrough\":false}],\"text\":\"888888888888888\"}"},{"id":"ChwKGkNOX2MwYnFkbW9jREZYM0N3Z1FkYkc4RWhB","videoId":"ZDHT_6Z6KPg","userId":"UCV7pAnoqiqRSEUq7wAt_pnA","timestamp":1720537446664,"videoOffsetTimeMsec":"3608857","jsonMessage":"{\"runs\":[{\"text\":\"好~\",\"bold\":false,\"italics\":false,\"strikethrough\":false}],\"text\":\"好~\"}"},{"id":"ChwKGkNNdTgyNGl6bW9jREZYM0N3Z1FkYkc4RWhB","videoId":"ZDHT_6Z6KPg","userId":"UCV7pAnoqiqRSEUq7wAt_pnA","timestamp":1720543247542,"videoOffsetTimeMsec":"9409693","jsonMessage":"{\"runs\":[{\"text\":\"庫庫晚安~\",\"bold\":false,\"italics\":false,\"strikethrough\":false}],\"text\":\"庫庫晚安~\"}"},{"id":"ChwKGkNMR2J2S2Zsd29nREZldlN3Z1Fkb3kwQ2xR","videoId":"R3St9tvzXpM","userId":"UCV7pAnoqiqRSEUq7wAt_pnA","timestamp":1726329169857,"videoOffsetTimeMsec":"6255372","jsonMessage":"{\"runs\":[{\"text\":\"庫庫安安~\",\"bold\":false,\"italics\":false,\"strikethrough\":false}],\"text\":\"庫庫安安~\"}"},{"id":"ChwKGkNPUDJoc3Jsd29nREZaUTByUVlkeFg4TG1n","videoId":"R3St9tvzXpM","userId":"UCV7pAnoqiqRSEUq7wAt_pnA","timestamp":1726329242372,"videoOffsetTimeMsec":"6327874","jsonMessage":"{\"runs\":[{\"text\":\"UC2ZWggon1NOT2TGaVUMzY7A/5i8fZrnvGufD_9EPv7eemAE\",\"emoji\":{\"emoji_id\":\"UC2ZWggon1NOT2TGaVUMzY7A/5i8fZrnvGufD_9EPv7eemAE\",\"shortcuts\":[\":_haa:\",\":haa:\"],\"search_terms\":[\"_haa\",\"haa\"],\"image\":[{\"url\":\"https://yt3.ggpht.com/UG4oQs1FLHPajQXr5Z0-uD_wIph2uKdQBFDTmtQ-RsphmRCjN-fK4tegXJOi28Dl36lALBG7=w48-h48-c-k-nd\",\"width\":48,\"height\":48},{\"url\":\"https://yt3.ggpht.com/UG4oQs1FLHPajQXr5Z0-uD_wIph2uKdQBFDTmtQ-RsphmRCjN-fK4tegXJOi28Dl36lALBG7=w24-h24-c-k-nd\",\"width\":24,\"height\":24}],\"is_custom\":true}},{\"text\":\"UC2ZWggon1NOT2TGaVUMzY7A/5i8fZrnvGufD_9EPv7eemAE\",\"emoji\":{\"emoji_id\":\"UC2ZWggon1NOT2TGaVUMzY7A/5i8fZrnvGufD_9EPv7eemAE\",\"shortcuts\":[\":_haa:\",\":haa:\"],\"search_terms\":[\"_haa\",\"haa\"],\"image\":[{\"url\":\"https://yt3.ggpht.com/UG4oQs1FLHPajQXr5Z0-uD_wIph2uKdQBFDTmtQ-RsphmRCjN-fK4tegXJOi28Dl36lALBG7=w48-h48-c-k-nd\",\"width\":48,\"height\":48},{\"url\":\"https://yt3.ggpht.com/UG4oQs1FLHPajQXr5Z0-uD_wIph2uKdQBFDTmtQ-RsphmRCjN-fK4tegXJOi28Dl36lALBG7=w24-h24-c-k-nd\",\"width\":24,\"height\":24}],\"is_custom\":true}},{\"text\":\"UC2ZWggon1NOT2TGaVUMzY7A/5i8fZrnvGufD_9EPv7eemAE\",\"emoji\":{\"emoji_id\":\"UC2ZWggon1NOT2TGaVUMzY7A/5i8fZrnvGufD_9EPv7eemAE\",\"shortcuts\":[\":_haa:\",\":haa:\"],\"search_terms\":[\"_haa\",\"haa\"],\"image\":[{\"url\":\"https://yt3.ggpht.com/UG4oQs1FLHPajQXr5Z0-uD_wIph2uKdQBFDTmtQ-RsphmRCjN-fK4tegXJOi28Dl36lALBG7=w48-h48-c-k-nd\",\"width\":48,\"height\":48},{\"url\":\"https://yt3.ggpht.com/UG4oQs1FLHPajQXr5Z0-uD_wIph2uKdQBFDTmtQ-RsphmRCjN-fK4tegXJOi28Dl36lALBG7=w24-h24-c-k-nd\",\"width\":24,\"height\":24}],\"is_custom\":true}},{\"text\":\"UC2ZWggon1NOT2TGaVUMzY7A/5i8fZrnvGufD_9EPv7eemAE\",\"emoji\":{\"emoji_id\":\"UC2ZWggon1NOT2TGaVUMzY7A/5i8fZrnvGufD_9EPv7eemAE\",\"shortcuts\":[\":_haa:\",\":haa:\"],\"search_terms\":[\"_haa\",\"haa\"],\"image\":[{\"url\":\"https://yt3.ggpht.com/UG4oQs1FLHPajQXr5Z0-uD_wIph2uKdQBFDTmtQ-RsphmRCjN-fK4tegXJOi28Dl36lALBG7=w48-h48-c-k-nd\",\"width\":48,\"height\":48},{\"url\":\"https://yt3.ggpht.com/UG4oQs1FLHPajQXr5Z0-uD_wIph2uKdQBFDTmtQ-RsphmRCjN-fK4tegXJOi28Dl36lALBG7=w24-h24-c-k-nd\",\"width\":24,\"height\":24}],\"is_custom\":true}},{\"text\":\"UC2ZWggon1NOT2TGaVUMzY7A/5i8fZrnvGufD_9EPv7eemAE\",\"emoji\":{\"emoji_id\":\"UC2ZWggon1NOT2TGaVUMzY7A/5i8fZrnvGufD_9EPv7eemAE\",\"shortcuts\":[\":_haa:\",\":haa:\"],\"search_terms\":[\"_haa\",\"haa\"],\"image\":[{\"url\":\"https://yt3.ggpht.com/UG4oQs1FLHPajQXr5Z0-uD_wIph2uKdQBFDTmtQ-RsphmRCjN-fK4tegXJOi28Dl36lALBG7=w48-h48-c-k-nd\",\"width\":48,\"height\":48},{\"url\":\"https://yt3.ggpht.com/UG4oQs1FLHPajQXr5Z0-uD_wIph2uKdQBFDTmtQ-RsphmRCjN-fK4tegXJOi28Dl36lALBG7=w24-h24-c-k-nd\",\"width\":24,\"height\":24}],\"is_custom\":true}},{\"text\":\"UC2ZWggon1NOT2TGaVUMzY7A/5i8fZrnvGufD_9EPv7eemAE\",\"emoji\":{\"emoji_id\":\"UC2ZWggon1NOT2TGaVUMzY7A/5i8fZrnvGufD_9EPv7eemAE\",\"shortcuts\":[\":_haa:\",\":haa:\"],\"search_terms\":[\"_haa\",\"haa\"],\"image\":[{\"url\":\"https://yt3.ggpht.com/UG4oQs1FLHPajQXr5Z0-uD_wIph2uKdQBFDTmtQ-RsphmRCjN-fK4tegXJOi28Dl36lALBG7=w48-h48-c-k-nd\",\"width\":48,\"height\":48},{\"url\":\"https://yt3.ggpht.com/UG4oQs1FLHPajQXr5Z0-uD_wIph2uKdQBFDTmtQ-RsphmRCjN-fK4tegXJOi28Dl36lALBG7=w24-h24-c-k-nd\",\"width\":24,\"height\":24}],\"is_custom\":true}}],\"text\":\"UC2ZWggon1NOT2TGaVUMzY7A/5i8fZrnvGufD_9EPv7eemAEUC2ZWggon1NOT2TGaVUMzY7A/5i8fZrnvGufD_9EPv7eemAEUC2ZWggon1NOT2TGaVUMzY7A/5i8fZrnvGufD_9EPv7eemAEUC2ZWggon1NOT2TGaVUMzY7A/5i8fZrnvGufD_9EPv7eemAEUC2ZWggon1NOT2TGaVUMzY7A/5i8fZrnvGufD_9EPv7eemAEUC2ZWggon1NOT2TGaVUMzY7A/5i8fZrnvGufD_9EPv7eemAE\"}"},{"id":"ChwKGkNNMmZpc0Rwd29nREZUM0V3Z1FkMXFjVnRn","videoId":"R3St9tvzXpM","userId":"UCV7pAnoqiqRSEUq7wAt_pnA","timestamp":1726330295196,"videoOffsetTimeMsec":"7380739","jsonMessage":"{\"runs\":[{\"text\":\"庫庫辛苦了\",\"bold\":false,\"italics\":false,\"strikethrough\":false}],\"text\":\"庫庫辛苦了\"}"},{"id":"ChwKGkNMcmN0c0xwd29nREZmTVdyUVlkQ1dBUlZB","videoId":"R3St9tvzXpM","userId":"UCV7pAnoqiqRSEUq7wAt_pnA","timestamp":1726330300133,"videoOffsetTimeMsec":"7385647","jsonMessage":"{\"runs\":[{\"text\":\"88888888888888\",\"bold\":false,\"italics\":false,\"strikethrough\":false}],\"text\":\"88888888888888\"}"},{"id":"ChwKGkNLblQ2c3o4X29nREZXdk93Z1FkNHhZd1V3","videoId":"VduWTqK6Cms","userId":"UCV7pAnoqiqRSEUq7wAt_pnA","timestamp":1728397006523,"videoOffsetTimeMsec":"935114","jsonMessage":"{\"runs\":[{\"text\":\"庫庫安安\",\"bold\":false,\"italics\":false,\"strikethrough\":false}],\"text\":\"庫庫安安\"}"},{"id":"ChwKGkNJdlVoZFg4X29nREZZUWhyUVlkdXpVWmlR","videoId":"VduWTqK6Cms","userId":"UCV7pAnoqiqRSEUq7wAt_pnA","timestamp":1728397023744,"videoOffsetTimeMsec":"952317","jsonMessage":"{\"runs\":[{\"text\":\"兔子四隻啦\",\"bold\":false,\"italics\":false,\"strikethrough\":false}],\"text\":\"兔子四隻啦\"}"},{"id":"ChwKGkNKZk5odWFYXzRnREZjVU5yUVlkVzhBSzFB","videoId":"VduWTqK6Cms","userId":"UCV7pAnoqiqRSEUq7wAt_pnA","timestamp":1728404307169,"videoOffsetTimeMsec":"8232047","jsonMessage":"{\"runs\":[{\"text\":\"8888888888888888888\",\"bold\":false,\"italics\":false,\"strikethrough\":false}],\"text\":\"8888888888888888888\"}"},{"id":"ChwKGkNPbl9uSW1EaVlrREZYd1dyUVlkVmowSjBn","videoId":"yiSxByO0or0","userId":"UCV7pAnoqiqRSEUq7wAt_pnA","timestamp":1728742341167,"videoOffsetTimeMsec":"717813","jsonMessage":"{\"runs\":[{\"text\":\"12了\",\"bold\":false,\"italics\":false,\"strikethrough\":false}],\"text\":\"12了\"}"},{"id":"ChwKGkNPcUQtWm1FaVlrREZaZ19yUVlkWEU4M19n","videoId":"yiSxByO0or0","userId":"UCV7pAnoqiqRSEUq7wAt_pnA","timestamp":1728742644665,"videoOffsetTimeMsec":"1021251","jsonMessage":"{\"runs\":[{\"text\":\"????????\",\"bold\":false,\"italics\":false,\"strikethrough\":false}],\"text\":\"????????\"}"},{"id":"ChwKGkNPNkM3TGFFaVlrREZhZ01yUVlkWnkwME9R","videoId":"yiSxByO0or0","userId":"UCV7pAnoqiqRSEUq7wAt_pnA","timestamp":1728742705268,"videoOffsetTimeMsec":"1081878","jsonMessage":"{\"runs\":[{\"text\":\"太瑟琴的啦\",\"bold\":false,\"italics\":false,\"strikethrough\":false}],\"text\":\"太瑟琴的啦\"}"},{"id":"ChwKGkNJQ29uTHVUaVlrREZkSUtyUVlkd05JSHJB","videoId":"yiSxByO0or0","userId":"UCV7pAnoqiqRSEUq7wAt_pnA","timestamp":1728746740990,"videoOffsetTimeMsec":"5117596","jsonMessage":"{\"runs\":[{\"text\":\"庫庫晚安~\",\"bold\":false,\"italics\":false,\"strikethrough\":false}],\"text\":\"庫庫晚安~\"}"},{"id":"ChwKGkNOaUJzTWVUaVlrREZXNHlyUVlkZV8wdjln","videoId":"yiSxByO0or0","userId":"UCV7pAnoqiqRSEUq7wAt_pnA","timestamp":1728746766474,"videoOffsetTimeMsec":"5143099","jsonMessage":"{\"runs\":[{\"text\":\"GG君\",\"bold\":false,\"italics\":false,\"strikethrough\":false}],\"text\":\"GG君\"}"},{"id":"ChwKGkNLRGY5UFNVb29rREZSb3ZyUVlkQ2dJUVVn","videoId":"mMOJOKkZyJ0","userId":"UCV7pAnoqiqRSEUq7wAt_pnA","timestamp":1729606123862,"videoOffsetTimeMsec":"32473","jsonMessage":"{\"runs\":[{\"text\":\"安安~\",\"bold\":false,\"italics\":false,\"strikethrough\":false}],\"text\":\"安安~\"}"},{"id":"ChwKGkNJVEt6UG1Vb29rREZjZ0hyUVlkVEFJQ2dn","videoId":"mMOJOKkZyJ0","userId":"UCV7pAnoqiqRSEUq7wAt_pnA","timestamp":1729606133702,"videoOffsetTimeMsec":"42370","jsonMessage":"{\"runs\":[{\"text\":\"UC2ZWggon1NOT2TGaVUMzY7A/Sd72YauvG-GS8gSe_63wCA\",\"emoji\":{\"emoji_id\":\"UC2ZWggon1NOT2TGaVUMzY7A/Sd72YauvG-GS8gSe_63wCA\",\"shortcuts\":[\":_跳舞ㄌ:\",\":跳舞ㄌ:\"],\"search_terms\":[\"_跳舞ㄌ\",\"跳舞ㄌ\"],\"image\":[{\"url\":\"https://yt3.ggpht.com/WG7yLcVLWfuPpiIBEBFnWGM-ll_i4AlAV2YxVG-xqmTbUGpBHtIcrTMRTdka__alRuqsrTvlpQE=w48-h48-c-k-nd\",\"width\":48,\"height\":48},{\"url\":\"https://yt3.ggpht.com/WG7yLcVLWfuPpiIBEBFnWGM-ll_i4AlAV2YxVG-xqmTbUGpBHtIcrTMRTdka__alRuqsrTvlpQE=w24-h24-c-k-nd\",\"width\":24,\"height\":24}],\"is_custom\":true}},{\"text\":\"UC2ZWggon1NOT2TGaVUMzY7A/Sd72YauvG-GS8gSe_63wCA\",\"emoji\":{\"emoji_id\":\"UC2ZWggon1NOT2TGaVUMzY7A/Sd72YauvG-GS8gSe_63wCA\",\"shortcuts\":[\":_跳舞ㄌ:\",\":跳舞ㄌ:\"],\"search_terms\":[\"_跳舞ㄌ\",\"跳舞ㄌ\"],\"image\":[{\"url\":\"https://yt3.ggpht.com/WG7yLcVLWfuPpiIBEBFnWGM-ll_i4AlAV2YxVG-xqmTbUGpBHtIcrTMRTdka__alRuqsrTvlpQE=w48-h48-c-k-nd\",\"width\":48,\"height\":48},{\"url\":\"https://yt3.ggpht.com/WG7yLcVLWfuPpiIBEBFnWGM-ll_i4AlAV2YxVG-xqmTbUGpBHtIcrTMRTdka__alRuqsrTvlpQE=w24-h24-c-k-nd\",\"width\":24,\"height\":24}],\"is_custom\":true}},{\"text\":\"UC2ZWggon1NOT2TGaVUMzY7A/Sd72YauvG-GS8gSe_63wCA\",\"emoji\":{\"emoji_id\":\"UC2ZWggon1NOT2TGaVUMzY7A/Sd72YauvG-GS8gSe_63wCA\",\"shortcuts\":[\":_跳舞ㄌ:\",\":跳舞ㄌ:\"],\"search_terms\":[\"_跳舞ㄌ\",\"跳舞ㄌ\"],\"image\":[{\"url\":\"https://yt3.ggpht.com/WG7yLcVLWfuPpiIBEBFnWGM-ll_i4AlAV2YxVG-xqmTbUGpBHtIcrTMRTdka__alRuqsrTvlpQE=w48-h48-c-k-nd\",\"width\":48,\"height\":48},{\"url\":\"https://yt3.ggpht.com/WG7yLcVLWfuPpiIBEBFnWGM-ll_i4AlAV2YxVG-xqmTbUGpBHtIcrTMRTdka__alRuqsrTvlpQE=w24-h24-c-k-nd\",\"width\":24,\"height\":24}],\"is_custom\":true}},{\"text\":\"UC2ZWggon1NOT2TGaVUMzY7A/Sd72YauvG-GS8gSe_63wCA\",\"emoji\":{\"emoji_id\":\"UC2ZWggon1NOT2TGaVUMzY7A/Sd72YauvG-GS8gSe_63wCA\",\"shortcuts\":[\":_跳舞ㄌ:\",\":跳舞ㄌ:\"],\"search_terms\":[\"_跳舞ㄌ\",\"跳舞ㄌ\"],\"image\":[{\"url\":\"https://yt3.ggpht.com/WG7yLcVLWfuPpiIBEBFnWGM-ll_i4AlAV2YxVG-xqmTbUGpBHtIcrTMRTdka__alRuqsrTvlpQE=w48-h48-c-k-nd\",\"width\":48,\"height\":48},{\"url\":\"https://yt3.ggpht.com/WG7yLcVLWfuPpiIBEBFnWGM-ll_i4AlAV2YxVG-xqmTbUGpBHtIcrTMRTdka__alRuqsrTvlpQE=w24-h24-c-k-nd\",\"width\":24,\"height\":24}],\"is_custom\":true}},{\"text\":\"UC2ZWggon1NOT2TGaVUMzY7A/Sd72YauvG-GS8gSe_63wCA\",\"emoji\":{\"emoji_id\":\"UC2ZWggon1NOT2TGaVUMzY7A/Sd72YauvG-GS8gSe_63wCA\",\"shortcuts\":[\":_跳舞ㄌ:\",\":跳舞ㄌ:\"],\"search_terms\":[\"_跳舞ㄌ\",\"跳舞ㄌ\"],\"image\":[{\"url\":\"https://yt3.ggpht.com/WG7yLcVLWfuPpiIBEBFnWGM-ll_i4AlAV2YxVG-xqmTbUGpBHtIcrTMRTdka__alRuqsrTvlpQE=w48-h48-c-k-nd\",\"width\":48,\"height\":48},{\"url\":\"https://yt3.ggpht.com/WG7yLcVLWfuPpiIBEBFnWGM-ll_i4AlAV2YxVG-xqmTbUGpBHtIcrTMRTdka__alRuqsrTvlpQE=w24-h24-c-k-nd\",\"width\":24,\"height\":24}],\"is_custom\":true}}],\"text\":\"UC2ZWggon1NOT2TGaVUMzY7A/Sd72YauvG-GS8gSe_63wCAUC2ZWggon1NOT2TGaVUMzY7A/Sd72YauvG-GS8gSe_63wCAUC2ZWggon1NOT2TGaVUMzY7A/Sd72YauvG-GS8gSe_63wCAUC2ZWggon1NOT2TGaVUMzY7A/Sd72YauvG-GS8gSe_63wCAUC2ZWggon1NOT2TGaVUMzY7A/Sd72YauvG-GS8gSe_63wCA\"}"},{"id":"ChwKGkNPYUpyZnlXb29rREZYbkJ3Z1FkYWhvUlZ3","videoId":"mMOJOKkZyJ0","userId":"UCV7pAnoqiqRSEUq7wAt_pnA","timestamp":1729606676346,"videoOffsetTimeMsec":"585019","jsonMessage":"{\"runs\":[{\"text\":\"UC2ZWggon1NOT2TGaVUMzY7A/5i8fZrnvGufD_9EPv7eemAE\",\"emoji\":{\"emoji_id\":\"UC2ZWggon1NOT2TGaVUMzY7A/5i8fZrnvGufD_9EPv7eemAE\",\"shortcuts\":[\":_haa:\",\":haa:\"],\"search_terms\":[\"_haa\",\"haa\"],\"image\":[{\"url\":\"https://yt3.ggpht.com/UG4oQs1FLHPajQXr5Z0-uD_wIph2uKdQBFDTmtQ-RsphmRCjN-fK4tegXJOi28Dl36lALBG7=w48-h48-c-k-nd\",\"width\":48,\"height\":48},{\"url\":\"https://yt3.ggpht.com/UG4oQs1FLHPajQXr5Z0-uD_wIph2uKdQBFDTmtQ-RsphmRCjN-fK4tegXJOi28Dl36lALBG7=w24-h24-c-k-nd\",\"width\":24,\"height\":24}],\"is_custom\":true}},{\"text\":\"UC2ZWggon1NOT2TGaVUMzY7A/5i8fZrnvGufD_9EPv7eemAE\",\"emoji\":{\"emoji_id\":\"UC2ZWggon1NOT2TGaVUMzY7A/5i8fZrnvGufD_9EPv7eemAE\",\"shortcuts\":[\":_haa:\",\":haa:\"],\"search_terms\":[\"_haa\",\"haa\"],\"image\":[{\"url\":\"https://yt3.ggpht.com/UG4oQs1FLHPajQXr5Z0-uD_wIph2uKdQBFDTmtQ-RsphmRCjN-fK4tegXJOi28Dl36lALBG7=w48-h48-c-k-nd\",\"width\":48,\"height\":48},{\"url\":\"https://yt3.ggpht.com/UG4oQs1FLHPajQXr5Z0-uD_wIph2uKdQBFDTmtQ-RsphmRCjN-fK4tegXJOi28Dl36lALBG7=w24-h24-c-k-nd\",\"width\":24,\"height\":24}],\"is_custom\":true}},{\"text\":\"UC2ZWggon1NOT2TGaVUMzY7A/5i8fZrnvGufD_9EPv7eemAE\",\"emoji\":{\"emoji_id\":\"UC2ZWggon1NOT2TGaVUMzY7A/5i8fZrnvGufD_9EPv7eemAE\",\"shortcuts\":[\":_haa:\",\":haa:\"],\"search_terms\":[\"_haa\",\"haa\"],\"image\":[{\"url\":\"https://yt3.ggpht.com/UG4oQs1FLHPajQXr5Z0-uD_wIph2uKdQBFDTmtQ-RsphmRCjN-fK4tegXJOi28Dl36lALBG7=w48-h48-c-k-nd\",\"width\":48,\"height\":48},{\"url\":\"https://yt3.ggpht.com/UG4oQs1FLHPajQXr5Z0-uD_wIph2uKdQBFDTmtQ-RsphmRCjN-fK4tegXJOi28Dl36lALBG7=w24-h24-c-k-nd\",\"width\":24,\"height\":24}],\"is_custom\":true}}],\"text\":\"UC2ZWggon1NOT2TGaVUMzY7A/5i8fZrnvGufD_9EPv7eemAEUC2ZWggon1NOT2TGaVUMzY7A/5i8fZrnvGufD_9EPv7eemAEUC2ZWggon1NOT2TGaVUMzY7A/5i8fZrnvGufD_9EPv7eemAE\"}"},{"id":"ChwKGkNPWFkwT0h3czRrREZiZk93Z1FkVzVvRmNR","videoId":"8Rr-DISVcEM","userId":"UCV7pAnoqiqRSEUq7wAt_pnA","timestamp":1730214895039,"videoOffsetTimeMsec":"4327810","jsonMessage":"{\"runs\":[{\"text\":\"庫庫早安~\",\"bold\":false,\"italics\":false,\"strikethrough\":false}],\"text\":\"庫庫早安~\"}"}]