[{"id":"ChwKGkNMSzl1YVhOeUlJREZldkJ3Z1FkQ0JrTi1R","videoId":"a_THhJ0Ed5Q","userId":"UC9FilkLtruQbj46Sek8bygw","timestamp":1700140602544,"videoOffsetTimeMsec":"967173","jsonMessage":"{\"runs\":[{\"text\":\"安安\",\"bold\":false,\"italics\":false,\"strikethrough\":false}],\"text\":\"安安\"}"},{"id":"ChwKGkNNbmJxSXlkMElJREZaYkN3Z1FkSE5JSGxB","videoId":"uZgAcQepenI","userId":"UC9FilkLtruQbj46Sek8bygw","timestamp":1700402542845,"videoOffsetTimeMsec":"128328","jsonMessage":"{\"runs\":[{\"text\":\"安安\",\"bold\":false,\"italics\":false,\"strikethrough\":false}],\"text\":\"安安\"}"},{"id":"ChwKGkNMckEwNVM5MElJREZSTEV3Z1FkT3E0R1d3","videoId":"uZgAcQepenI","userId":"UC9FilkLtruQbj46Sek8bygw","timestamp":1700411150254,"videoOffsetTimeMsec":"8735824","jsonMessage":"{\"runs\":[{\"text\":\"晚安\",\"bold\":false,\"italics\":false,\"strikethrough\":false}],\"text\":\"晚安\"}"},{"id":"ChwKGkNQLVgzT0M5MElJREZSTEV3Z1FkT3E0R1d3","videoId":"uZgAcQepenI","userId":"UC9FilkLtruQbj46Sek8bygw","timestamp":1700411309778,"videoOffsetTimeMsec":"8895237","jsonMessage":"{\"runs\":[{\"text\":\"晚安\",\"bold\":false,\"italics\":false,\"strikethrough\":false}],\"text\":\"晚安\"}"},{"id":"ChwKGkNJYkRoX3JsMTRJREZUbkR3Z1FkclF3T1NB","videoId":"SFFh2VCAmIc","userId":"UC9FilkLtruQbj46Sek8bygw","timestamp":1700662618508,"videoOffsetTimeMsec":"932108","jsonMessage":"{\"runs\":[{\"text\":\"安安\",\"bold\":false,\"italics\":false,\"strikethrough\":false}],\"text\":\"安安\"}"}]