[{"id":"ChwKGkNNdTR4WmV2Z29FREZUclF3Z1FkWkV3TU1n","videoId":"ROXZZtwI8wY","userId":"UCxhfqZ3A0QbY7GNOWAZtvrA","timestamp":1693329292114,"videoOffsetTimeMsec":"9683710","jsonMessage":"{\"runs\":[{\"text\":\"好的芋头\",\"bold\":false,\"italics\":false,\"strikethrough\":false}],\"text\":\"好的芋头\"}"},{"id":"ChwKGkNORHI0SkN6Z29FREZYX0R3Z1FkRFVVRFNn","videoId":"ROXZZtwI8wY","userId":"UCxhfqZ3A0QbY7GNOWAZtvrA","timestamp":1693330351623,"videoOffsetTimeMsec":"10743188","jsonMessage":"{\"runs\":[{\"text\":\"恭喜通关\",\"bold\":false,\"italics\":false,\"strikethrough\":false}],\"text\":\"恭喜通关\"}"},{"id":"ChwKGkNNS1JucjJDajRFREZjckN3Z1FkWGxNT2tn","videoId":"om4YiZF-wZw","userId":"UCxhfqZ3A0QbY7GNOWAZtvrA","timestamp":1693763968170,"videoOffsetTimeMsec":"3446669","jsonMessage":"{\"runs\":[{\"text\":\"24\",\"bold\":false,\"italics\":false,\"strikethrough\":false}],\"text\":\"24\"}"},{"id":"ChwKGkNPbWQwcHlEajRFREZYX0R3Z1FkVWt3SkxB","videoId":"om4YiZF-wZw","userId":"UCxhfqZ3A0QbY7GNOWAZtvrA","timestamp":1693764168250,"videoOffsetTimeMsec":"3646758","jsonMessage":"{\"runs\":[{\"text\":\"大葱呢\",\"bold\":false,\"italics\":false,\"strikethrough\":false}],\"text\":\"大葱呢\"}"},{"id":"ChwKGkNNU0tpTW10dVlFREZackJ3Z1FkLTB3SlVn","videoId":"R1gsMtDqrw8","userId":"UCxhfqZ3A0QbY7GNOWAZtvrA","timestamp":1695218644716,"videoOffsetTimeMsec":"147266","jsonMessage":"{\"runs\":[{\"text\":\"庫庫安安\",\"bold\":false,\"italics\":false,\"strikethrough\":false}],\"text\":\"庫庫安安\"}"}]