[{"id":"ChwKGkNQdWM3dkNQNUlBREZjSEJ3Z1Fkdi1RSFdR","videoId":"MOgVolxywmI","userId":"UCbaEd9B4ApB8sF_jFU15R8w","timestamp":1692290097332,"videoOffsetTimeMsec":"8624480","jsonMessage":"{\"runs\":[{\"text\":\"當時美國帶來的\",\"bold\":false,\"italics\":false,\"strikethrough\":false}],\"text\":\"當時美國帶來的\"}"},{"id":"ChwKGkNNN3UxWWFRNUlBREZYWEJ3Z1FkWTBrT2xB","videoId":"MOgVolxywmI","userId":"UCbaEd9B4ApB8sF_jFU15R8w","timestamp":1692290143070,"videoOffsetTimeMsec":"8670274","jsonMessage":"{\"runs\":[{\"text\":\"高溫逝三溫暖\",\"bold\":false,\"italics\":false,\"strikethrough\":false}],\"text\":\"高溫逝三溫暖\"}"},{"id":"ChwKGkNJWGZ3ZDZRNUlBREZTREJ3Z1FkcGdvQmxR","videoId":"MOgVolxywmI","userId":"UCbaEd9B4ApB8sF_jFU15R8w","timestamp":1692290327291,"videoOffsetTimeMsec":"8854529","jsonMessage":"{\"runs\":[{\"text\":\"我剛畫素描覺得畫很爛，看到這個突然覺得自己畫很好\",\"bold\":false,\"italics\":false,\"strikethrough\":false}],\"text\":\"我剛畫素描覺得畫很爛，看到這個突然覺得自己畫很好\"}"},{"id":"ChwKGkNMV3c2dU9SNUlBREZRN1B3Z1FkbENzRTdn","videoId":"MOgVolxywmI","userId":"UCbaEd9B4ApB8sF_jFU15R8w","timestamp":1692290606876,"videoOffsetTimeMsec":"9134069","jsonMessage":"{\"runs\":[{\"text\":\"我記得美國有個女孩隨便畫一畫就被收藏家花16萬美元收購\",\"bold\":false,\"italics\":false,\"strikethrough\":false}],\"text\":\"我記得美國有個女孩隨便畫一畫就被收藏家花16萬美元收購\"}"},{"id":"ChwKGkNQenNoLUtTNUlBREZYWEJ3Z1FkWTBrT2xB","videoId":"MOgVolxywmI","userId":"UCbaEd9B4ApB8sF_jFU15R8w","timestamp":1692290871604,"videoOffsetTimeMsec":"9398816","jsonMessage":"{\"runs\":[{\"text\":\"我要回去畫素描ㄌ庫庫8181\",\"bold\":false,\"italics\":false,\"strikethrough\":false}],\"text\":\"我要回去畫素描ㄌ庫庫8181\"}"},{"id":"ChwKGkNPZUE4cFhvX0lBREZYN0N3Z1FkcmtZRzJn","videoId":"RpLK9o1tdYk","userId":"UCbaEd9B4ApB8sF_jFU15R8w","timestamp":1693138431045,"videoOffsetTimeMsec":"7813524","jsonMessage":"{\"runs\":[{\"text\":\"ㄤㄤ\",\"bold\":false,\"italics\":false,\"strikethrough\":false}],\"text\":\"ㄤㄤ\"}"},{"id":"ChwKGkNNR0Nvc0hwX0lBREZWb1RyUVlkT2FVR1F3","videoId":"RpLK9o1tdYk","userId":"UCbaEd9B4ApB8sF_jFU15R8w","timestamp":1693138790439,"videoOffsetTimeMsec":"8172783","jsonMessage":"{\"runs\":[{\"text\":\"這叫胖???\",\"bold\":false,\"italics\":false,\"strikethrough\":false}],\"text\":\"這叫胖???\"}"},{"id":"ChwKGkNKT0k3ZXZwX0lBREZWb1RyUVlkT2FVR1F3","videoId":"RpLK9o1tdYk","userId":"UCbaEd9B4ApB8sF_jFU15R8w","timestamp":1693138879754,"videoOffsetTimeMsec":"8262132","jsonMessage":"{\"runs\":[{\"text\":\"有少女心的貓\",\"bold\":false,\"italics\":false,\"strikethrough\":false}],\"text\":\"有少女心的貓\"}"},{"id":"ChwKGkNKYmN6STNyX0lBREZhN0F3Z1FkSGg0S0N3","videoId":"RpLK9o1tdYk","userId":"UCbaEd9B4ApB8sF_jFU15R8w","timestamp":1693139218960,"videoOffsetTimeMsec":"8601495","jsonMessage":"{\"runs\":[{\"text\":\"膝蓋奶\",\"bold\":false,\"italics\":false,\"strikethrough\":false}],\"text\":\"膝蓋奶\"}"},{"id":"ChwKGkNOV2RnOVhzX0lBREZUN1B3Z1FkcVZVRVF3","videoId":"RpLK9o1tdYk","userId":"UCbaEd9B4ApB8sF_jFU15R8w","timestamp":1693139637188,"videoOffsetTimeMsec":"9019594","jsonMessage":"{\"runs\":[{\"text\":\"可能因為庫庫有抖S氣場\",\"bold\":false,\"italics\":false,\"strikethrough\":false}],\"text\":\"可能因為庫庫有抖S氣場\"}"},{"id":"ChwKGkNQV0NoNlh0X0lBREZmYkJ3Z1FkWnFZRmZB","videoId":"RpLK9o1tdYk","userId":"UCbaEd9B4ApB8sF_jFU15R8w","timestamp":1693139805029,"videoOffsetTimeMsec":"9187502","jsonMessage":"{\"runs\":[{\"text\":\"那如果是監獄出來的呢\",\"bold\":false,\"italics\":false,\"strikethrough\":false}],\"text\":\"那如果是監獄出來的呢\"}"},{"id":"ChwKGkNOV0FnOFR0X0lBREZVTV9yUVlkVEo4RGhR","videoId":"RpLK9o1tdYk","userId":"UCbaEd9B4ApB8sF_jFU15R8w","timestamp":1693139869966,"videoOffsetTimeMsec":"9252414","jsonMessage":"{\"runs\":[{\"text\":\"30號\",\"bold\":false,\"italics\":false,\"strikethrough\":false}],\"text\":\"30號\"}"},{"id":"ChwKGkNPR0p5Nm51X0lBREZjWER3Z1FkaGlBRGZB","videoId":"RpLK9o1tdYk","userId":"UCbaEd9B4ApB8sF_jFU15R8w","timestamp":1693140082957,"videoOffsetTimeMsec":"9465464","jsonMessage":"{\"runs\":[{\"text\":\"芋頭姊姊，我要升小班ㄌ\",\"bold\":false,\"italics\":false,\"strikethrough\":false}],\"text\":\"芋頭姊姊，我要升小班ㄌ\"}"},{"id":"ChwKGkNMcW1ydnJ1X0lBREZhVEN3Z1FkMDRvSDdB","videoId":"RpLK9o1tdYk","userId":"UCbaEd9B4ApB8sF_jFU15R8w","timestamp":1693140252357,"videoOffsetTimeMsec":"9634844","jsonMessage":"{\"runs\":[{\"text\":\"送我家貓\",\"bold\":false,\"italics\":false,\"strikethrough\":false}],\"text\":\"送我家貓\"}"},{"id":"ChwKGkNPdms4dmZ2X0lBREZRREN3Z1FkWWk4Q3NB","videoId":"RpLK9o1tdYk","userId":"UCbaEd9B4ApB8sF_jFU15R8w","timestamp":1693140515640,"videoOffsetTimeMsec":"9898034","jsonMessage":"{\"runs\":[{\"text\":\"台中要去吃慶記阿\",\"bold\":false,\"italics\":false,\"strikethrough\":false}],\"text\":\"台中要去吃慶記阿\"}"},{"id":"ChwKGkNJcUZ1Y1h3X0lBREZUN1B3Z1FkcVZVRVF3","videoId":"RpLK9o1tdYk","userId":"UCbaEd9B4ApB8sF_jFU15R8w","timestamp":1693140678257,"videoOffsetTimeMsec":"10060770","jsonMessage":"{\"runs\":[{\"text\":\"辦柬埔寨\",\"bold\":false,\"italics\":false,\"strikethrough\":false}],\"text\":\"辦柬埔寨\"}"},{"id":"ChwKGkNJbTEzdjN3X0lBREZjckN3Z1FkcWdFRHBn","videoId":"RpLK9o1tdYk","userId":"UCbaEd9B4ApB8sF_jFU15R8w","timestamp":1693140796307,"videoOffsetTimeMsec":"10178806","jsonMessage":"{\"runs\":[{\"text\":\"辦濁水溪中央，搭船過去\",\"bold\":false,\"italics\":false,\"strikethrough\":false}],\"text\":\"辦濁水溪中央，搭船過去\"}"},{"id":"ChwKGkNJaWQ1TUx5X0lBREZYWEJ3Z1FkZlFzRzJR","videoId":"RpLK9o1tdYk","userId":"UCbaEd9B4ApB8sF_jFU15R8w","timestamp":1693141209545,"videoOffsetTimeMsec":"10591921","jsonMessage":"{\"runs\":[{\"text\":\"大麻廠商能聯名嗎\",\"bold\":false,\"italics\":false,\"strikethrough\":false}],\"text\":\"大麻廠商能聯名嗎\"}"},{"id":"ChwKGkNLeVRyb1R6X0lBREZjSEJ3Z1Fka1N3TnVn","videoId":"RpLK9o1tdYk","userId":"UCbaEd9B4ApB8sF_jFU15R8w","timestamp":1693141347067,"videoOffsetTimeMsec":"10729540","jsonMessage":"{\"runs\":[{\"text\":\"飯裡投毒\",\"bold\":false,\"italics\":false,\"strikethrough\":false}],\"text\":\"飯裡投毒\"}"},{"id":"ChwKGkNQREV5YUx6X0lBREZmYkJ3Z1FkWnFZRmZB","videoId":"RpLK9o1tdYk","userId":"UCbaEd9B4ApB8sF_jFU15R8w","timestamp":1693141410437,"videoOffsetTimeMsec":"10792937","jsonMessage":"{\"runs\":[{\"text\":\"我不想騙人\",\"bold\":false,\"italics\":false,\"strikethrough\":false}],\"text\":\"我不想騙人\"}"},{"id":"ChwKGkNNano2TmZ6X0lBREZZVEN3Z1Fkb0U0RXFB","videoId":"RpLK9o1tdYk","userId":"UCbaEd9B4ApB8sF_jFU15R8w","timestamp":1693141522095,"videoOffsetTimeMsec":"10904450","jsonMessage":"{\"runs\":[{\"text\":\"13月32號\",\"bold\":false,\"italics\":false,\"strikethrough\":false}],\"text\":\"13月32號\"}"},{"id":"ChwKGkNMcnYwZDMwX0lBREZjWER3Z1FkaGlBRGZB","videoId":"RpLK9o1tdYk","userId":"UCbaEd9B4ApB8sF_jFU15R8w","timestamp":1693141802735,"videoOffsetTimeMsec":"11185079","jsonMessage":"{\"runs\":[{\"text\":\"活了13年，連一隻狗都不如\",\"bold\":false,\"italics\":false,\"strikethrough\":false}],\"text\":\"活了13年，連一隻狗都不如\"}"},{"id":"ChwKGkNJUE03ZEQxX0lBREZWblJ3Z1FkeXdZRWJ3","videoId":"RpLK9o1tdYk","userId":"UCbaEd9B4ApB8sF_jFU15R8w","timestamp":1693142044363,"videoOffsetTimeMsec":"11426836","jsonMessage":"{\"runs\":[{\"text\":\"好好，都有媽媽\",\"bold\":false,\"italics\":false,\"strikethrough\":false}],\"text\":\"好好，都有媽媽\"}"},{"id":"ChwKGkNPN0t0T2oxX0lBREZRN1B3Z1Fkb0VzRVVn","videoId":"RpLK9o1tdYk","userId":"UCbaEd9B4ApB8sF_jFU15R8w","timestamp":1693142093762,"videoOffsetTimeMsec":"11476091","jsonMessage":"{\"runs\":[{\"text\":\"我也想要個媽媽RRRR\",\"bold\":false,\"italics\":false,\"strikethrough\":false}],\"text\":\"我也想要個媽媽RRRR\"}"},{"id":"ChwKGkNOR2c1N0gyX0lBREZhN0F3Z1FkSGg0S0N3","videoId":"RpLK9o1tdYk","userId":"UCbaEd9B4ApB8sF_jFU15R8w","timestamp":1693142247677,"videoOffsetTimeMsec":"11630001","jsonMessage":"{\"runs\":[{\"text\":\"我騎單車的，平常戴手套直接被曬成斑馬線\",\"bold\":false,\"italics\":false,\"strikethrough\":false}],\"text\":\"我騎單車的，平常戴手套直接被曬成斑馬線\"}"},{"id":"ChwKGkNLUE56YUg0X0lBREZWblJ3Z1FkeXdZRWJ3","videoId":"RpLK9o1tdYk","userId":"UCbaEd9B4ApB8sF_jFU15R8w","timestamp":1693142750581,"videoOffsetTimeMsec":"12133037","jsonMessage":"{\"runs\":[{\"text\":\"辦非洲他們還會倒貼你\",\"bold\":false,\"italics\":false,\"strikethrough\":false}],\"text\":\"辦非洲他們還會倒貼你\"}"},{"id":"ChwKGkNOR01ndVg0X0lBREZYX0R3Z1FkSEZ3Sk9n","videoId":"RpLK9o1tdYk","userId":"UCbaEd9B4ApB8sF_jFU15R8w","timestamp":1693142891944,"videoOffsetTimeMsec":"12274290","jsonMessage":"{\"runs\":[{\"text\":\"辦公廁\",\"bold\":false,\"italics\":false,\"strikethrough\":false}],\"text\":\"辦公廁\"}"},{"id":"ChwKGkNNQ2xzNVQ1X0lBREZUN1B3Z1FkcVZVRVF3","videoId":"RpLK9o1tdYk","userId":"UCbaEd9B4ApB8sF_jFU15R8w","timestamp":1693142991318,"videoOffsetTimeMsec":"12373700","jsonMessage":"{\"runs\":[{\"text\":\"淡水河裡降溫又消暑\",\"bold\":false,\"italics\":false,\"strikethrough\":false}],\"text\":\"淡水河裡降溫又消暑\"}"},{"id":"ChwKGkNPcVQtSV82X0lBREZYX0R3Z1FkSEZ3Sk9n","videoId":"RpLK9o1tdYk","userId":"UCbaEd9B4ApB8sF_jFU15R8w","timestamp":1693143250396,"videoOffsetTimeMsec":"12632780","jsonMessage":"{\"runs\":[{\"text\":\"猴子聖地\",\"bold\":false,\"italics\":false,\"strikethrough\":false}],\"text\":\"猴子聖地\"}"},{"id":"ChwKGkNKcnprcmo2X0lBREZZVEN3Z1Fkb0U0RXFB","videoId":"RpLK9o1tdYk","userId":"UCbaEd9B4ApB8sF_jFU15R8w","timestamp":1693143334724,"videoOffsetTimeMsec":"12711203","jsonMessage":"{\"runs\":[{\"text\":\"可以帶著Kuro出門，這樣就不怕ㄌ\",\"bold\":false,\"italics\":false,\"strikethrough\":false}],\"text\":\"可以帶著Kuro出門，這樣就不怕ㄌ\"}"},{"id":"ChwKGkNLWE8ydVg2X0lBREZRREN3Z1FkWWk4Q3NB","videoId":"RpLK9o1tdYk","userId":"UCbaEd9B4ApB8sF_jFU15R8w","timestamp":1693143430277,"videoOffsetTimeMsec":"12806746","jsonMessage":"{\"runs\":[{\"text\":\"燒給自己\",\"bold\":false,\"italics\":false,\"strikethrough\":false}],\"text\":\"燒給自己\"}"},{"id":"ChwKGkNPcUZpNWY3X0lBREZhN0F3Z1FkSGg0S0N3","videoId":"RpLK9o1tdYk","userId":"UCbaEd9B4ApB8sF_jFU15R8w","timestamp":1693143533824,"videoOffsetTimeMsec":"12910139","jsonMessage":"{\"runs\":[{\"text\":\"會不會有紙庫庫\",\"bold\":false,\"italics\":false,\"strikethrough\":false}],\"text\":\"會不會有紙庫庫\"}"},{"id":"ChwKGkNPLVJuOG43X0lBREZjSEJ3Z1Fka1N3TnVn","videoId":"RpLK9o1tdYk","userId":"UCbaEd9B4ApB8sF_jFU15R8w","timestamp":1693143639004,"videoOffsetTimeMsec":"13015410","jsonMessage":"{\"runs\":[{\"text\":\"我\",\"bold\":false,\"italics\":false,\"strikethrough\":false}],\"text\":\"我\"}"},{"id":"ChwKGkNKelJwY3o3X0lBREZYX0R3Z1FkSEZ3Sk9n","videoId":"RpLK9o1tdYk","userId":"UCbaEd9B4ApB8sF_jFU15R8w","timestamp":1693143645406,"videoOffsetTimeMsec":"13021734","jsonMessage":"{\"runs\":[{\"text\":\"沒下單\",\"bold\":false,\"italics\":false,\"strikethrough\":false}],\"text\":\"沒下單\"}"},{"id":"ChwKGkNKSEhxT0Q4X0lBREZjWER3Z1FkaGlBRGZB","videoId":"RpLK9o1tdYk","userId":"UCbaEd9B4ApB8sF_jFU15R8w","timestamp":1693143955831,"videoOffsetTimeMsec":"13332158","jsonMessage":"{\"runs\":[{\"text\":\"買包包送芋頭嗎\",\"bold\":false,\"italics\":false,\"strikethrough\":false}],\"text\":\"買包包送芋頭嗎\"}"},{"id":"ChwKGkNMLWRwdFQ5X0lBREZiVEN3Z1FkXy1RSDdR","videoId":"RpLK9o1tdYk","userId":"UCbaEd9B4ApB8sF_jFU15R8w","timestamp":1693144199066,"videoOffsetTimeMsec":"13575349","jsonMessage":"{\"runs\":[{\"text\":\"881\",\"bold\":false,\"italics\":false,\"strikethrough\":false}],\"text\":\"881\"}"},{"id":"ChwKGkNQRHdzLTM5X0lBREZUN1B3Z1FkcVZVRVF3","videoId":"RpLK9o1tdYk","userId":"UCbaEd9B4ApB8sF_jFU15R8w","timestamp":1693144251717,"videoOffsetTimeMsec":"13628151","jsonMessage":"{\"runs\":[{\"text\":\"881~\",\"bold\":false,\"italics\":false,\"strikethrough\":false}],\"text\":\"881~\"}"},{"id":"ChwKGkNJNlhfZW5YaElFREZSY19yUVlkaTFzTnl3","videoId":"QZ7Ap-5mq-k","userId":"UCbaEd9B4ApB8sF_jFU15R8w","timestamp":1693408921885,"videoOffsetTimeMsec":"4667265","jsonMessage":"{\"runs\":[{\"text\":\" 不是初見安安\",\"bold\":false,\"italics\":false,\"strikethrough\":false}],\"text\":\" 不是初見安安\"}"},{"id":"ChwKGkNOV0VuUFRaaElFREZjSEJ3Z1FkQW93S1l3","videoId":"QZ7Ap-5mq-k","userId":"UCbaEd9B4ApB8sF_jFU15R8w","timestamp":1693409480237,"videoOffsetTimeMsec":"5225770","jsonMessage":"{\"runs\":[{\"text\":\"老大知道導盲犬可入內是寫給導盲犬看，還是寫給盲人看的ㄇ\",\"bold\":false,\"italics\":false,\"strikethrough\":false}],\"text\":\"老大知道導盲犬可入內是寫給導盲犬看，還是寫給盲人看的ㄇ\"}"},{"id":"ChwKGkNLN2Q3S3piaElFREZjSEJ3Z1FkQW93S1l3","videoId":"QZ7Ap-5mq-k","userId":"UCbaEd9B4ApB8sF_jFU15R8w","timestamp":1693409867433,"videoOffsetTimeMsec":"5612967","jsonMessage":"{\"runs\":[{\"text\":\"物以類聚\",\"bold\":false,\"italics\":false,\"strikethrough\":false}],\"text\":\"物以類聚\"}"},{"id":"ChwKGkNKYVcxZV9iaElFREZYX0R3Z1Fka0lBTjBn","videoId":"QZ7Ap-5mq-k","userId":"UCbaEd9B4ApB8sF_jFU15R8w","timestamp":1693410007556,"videoOffsetTimeMsec":"5753112","jsonMessage":"{\"runs\":[{\"text\":\"沒有御姊音只有芋頭音\",\"bold\":false,\"italics\":false,\"strikethrough\":false}],\"text\":\"沒有御姊音只有芋頭音\"}"},{"id":"ChwKGkNMR1VfbzNjaElFREZUclF3Z1FkWF9rRnhB","videoId":"QZ7Ap-5mq-k","userId":"UCbaEd9B4ApB8sF_jFU15R8w","timestamp":1693410071148,"videoOffsetTimeMsec":"5816695","jsonMessage":"{\"runs\":[{\"text\":\"?\",\"bold\":false,\"italics\":false,\"strikethrough\":false}],\"text\":\"?\"}"},{"id":"ChwKGkNMMmwwclRjaElFREZUN1B3Z1FkUmdNS0VB","videoId":"QZ7Ap-5mq-k","userId":"UCbaEd9B4ApB8sF_jFU15R8w","timestamp":1693410152212,"videoOffsetTimeMsec":"5897801","jsonMessage":"{\"runs\":[{\"text\":\"衰老的芋頭\",\"bold\":false,\"italics\":false,\"strikethrough\":false}],\"text\":\"衰老的芋頭\"}"},{"id":"ChwKGkNOZjVrOV9kaElFREZYWEJ3Z1FkTHN3SXFR","videoId":"QZ7Ap-5mq-k","userId":"UCbaEd9B4ApB8sF_jFU15R8w","timestamp":1693410509807,"videoOffsetTimeMsec":"6255342","jsonMessage":"{\"runs\":[{\"text\":\"不打麻醉才是真勇者\",\"bold\":false,\"italics\":false,\"strikethrough\":false}],\"text\":\"不打麻醉才是真勇者\"}"},{"id":"ChwKGkNMR3MzSWplaElFREZjSEJ3Z1FkQW93S1l3","videoId":"QZ7Ap-5mq-k","userId":"UCbaEd9B4ApB8sF_jFU15R8w","timestamp":1693410596981,"videoOffsetTimeMsec":"6342578","jsonMessage":"{\"runs\":[{\"text\":\"可惜割完不能留下來\",\"bold\":false,\"italics\":false,\"strikethrough\":false}],\"text\":\"可惜割完不能留下來\"}"},{"id":"ChwKGkNKeXdndW5laElFREZRN1B3Z1Fkek1BSzhR","videoId":"QZ7Ap-5mq-k","userId":"UCbaEd9B4ApB8sF_jFU15R8w","timestamp":1693410798924,"videoOffsetTimeMsec":"6544445","jsonMessage":"{\"runs\":[{\"text\":\"那天Kuro想起了被人類支配的恐懼\",\"bold\":false,\"italics\":false,\"strikethrough\":false}],\"text\":\"那天Kuro想起了被人類支配的恐懼\"}"},{"id":"ChwKGkNKS3loYlRnaElFREZWb1RyUVlkM09BS0VB","videoId":"QZ7Ap-5mq-k","userId":"UCbaEd9B4ApB8sF_jFU15R8w","timestamp":1693411224697,"videoOffsetTimeMsec":"6970252","jsonMessage":"{\"runs\":[{\"text\":\"我外送就是叫大腸麵線......\",\"bold\":false,\"italics\":false,\"strikethrough\":false}],\"text\":\"我外送就是叫大腸麵線......\"}"},{"id":"ChwKGkNPNy16b0xoaElFREZUN1B3Z1FkUmdNS0VB","videoId":"QZ7Ap-5mq-k","userId":"UCbaEd9B4ApB8sF_jFU15R8w","timestamp":1693411389482,"videoOffsetTimeMsec":"7135014","jsonMessage":"{\"runs\":[{\"text\":\"滿滿ㄉ芋頭味\",\"bold\":false,\"italics\":false,\"strikethrough\":false}],\"text\":\"滿滿ㄉ芋頭味\"}"},{"id":"ChwKGkNOYi1tSl9oaElFREZTREJ3Z1FkQmNBTXF3","videoId":"QZ7Ap-5mq-k","userId":"UCbaEd9B4ApB8sF_jFU15R8w","timestamp":1693411449409,"videoOffsetTimeMsec":"7194918","jsonMessage":"{\"runs\":[{\"text\":\"叫Kuor吹\",\"bold\":false,\"italics\":false,\"strikethrough\":false}],\"text\":\"叫Kuor吹\"}"},{"id":"ChwKGkNNRFlzTjNoaElFREZjckN3Z1FkOWNnTk5B","videoId":"QZ7Ap-5mq-k","userId":"UCbaEd9B4ApB8sF_jFU15R8w","timestamp":1693411579827,"videoOffsetTimeMsec":"7325376","jsonMessage":"{\"runs\":[{\"text\":\"全自動耳膜爆破機\",\"bold\":false,\"italics\":false,\"strikethrough\":false}],\"text\":\"全自動耳膜爆破機\"}"},{"id":"ChwKGkNObXBzWjdpaElFREZjSEJ3Z1FkQW93S1l3","videoId":"QZ7Ap-5mq-k","userId":"UCbaEd9B4ApB8sF_jFU15R8w","timestamp":1693411716149,"videoOffsetTimeMsec":"7461747","jsonMessage":"{\"runs\":[{\"text\":\"Kuor脾氣好好，我家那隻連碰都不行\",\"bold\":false,\"italics\":false,\"strikethrough\":false}],\"text\":\"Kuor脾氣好好，我家那隻連碰都不行\"}"},{"id":"ChwKGkNLYXprcF9qaElFREZiM0R3Z1FkOFNzSGt3","videoId":"QZ7Ap-5mq-k","userId":"UCbaEd9B4ApB8sF_jFU15R8w","timestamp":1693411986176,"videoOffsetTimeMsec":"7731694","jsonMessage":"{\"runs\":[{\"text\":\"貓草線下聚會，醫院割包皮\",\"bold\":false,\"italics\":false,\"strikethrough\":false}],\"text\":\"貓草線下聚會，醫院割包皮\"}"},{"id":"ChwKGkNLblUyczNqaElFREZUN1B3Z1FkUmdNS0VB","videoId":"QZ7Ap-5mq-k","userId":"UCbaEd9B4ApB8sF_jFU15R8w","timestamp":1693412083827,"videoOffsetTimeMsec":"7829385","jsonMessage":"{\"runs\":[{\"text\":\"洨失的筆跡\",\"bold\":false,\"italics\":false,\"strikethrough\":false}],\"text\":\"洨失的筆跡\"}"},{"id":"ChwKGkNNdkxtOV9qaElFREZWb1RyUVlkM09BS0VB","videoId":"QZ7Ap-5mq-k","userId":"UCbaEd9B4ApB8sF_jFU15R8w","timestamp":1693412120538,"videoOffsetTimeMsec":"7866060","jsonMessage":"{\"runs\":[{\"text\":\"881\",\"bold\":false,\"italics\":false,\"strikethrough\":false}],\"text\":\"881\"}"},{"id":"ChwKGkNLYWN2LTNraElFREZYX0R3Z1Fka0lBTjBn","videoId":"QZ7Ap-5mq-k","userId":"UCbaEd9B4ApB8sF_jFU15R8w","timestamp":1693412418923,"videoOffsetTimeMsec":"8164414","jsonMessage":"{\"runs\":[{\"text\":\"88\",\"bold\":false,\"italics\":false,\"strikethrough\":false}],\"text\":\"88\"}"},{"id":"ChwKGkNObjl3TF8yam9FREZVTV9yUVlkT01BSGtn","videoId":"om4YiZF-wZw","userId":"UCbaEd9B4ApB8sF_jFU15R8w","timestamp":1693760751701,"videoOffsetTimeMsec":"230272","jsonMessage":"{\"runs\":[{\"text\":\"芋頭安安\",\"bold\":false,\"italics\":false,\"strikethrough\":false}],\"text\":\"芋頭安安\"}"},{"id":"ChwKGkNKTFpfT3ozam9FREZaN0R3Z1FkanhVTk1R","videoId":"om4YiZF-wZw","userId":"UCbaEd9B4ApB8sF_jFU15R8w","timestamp":1693761115487,"videoOffsetTimeMsec":"594105","jsonMessage":"{\"runs\":[{\"text\":\"芋頭ASMR\",\"bold\":false,\"italics\":false,\"strikethrough\":false}],\"text\":\"芋頭ASMR\"}"},{"id":"ChwKGkNLTHhoclhpbllFREZhMF9yUVlkR3k0SmlR","videoId":"5Z5uFOfWnh4","userId":"UCbaEd9B4ApB8sF_jFU15R8w","timestamp":1694270757178,"videoOffsetTimeMsec":"2683350","jsonMessage":"{\"runs\":[{\"text\":\"芋頭安安\",\"bold\":false,\"italics\":false,\"strikethrough\":false}],\"text\":\"芋頭安安\"}"},{"id":"ChwKGkNNbnA3UFBpbllFREZjckN3Z1FkemlvS3Zn","videoId":"5Z5uFOfWnh4","userId":"UCbaEd9B4ApB8sF_jFU15R8w","timestamp":1694270888845,"videoOffsetTimeMsec":"2815066","jsonMessage":"{\"runs\":[{\"text\":\"這種東西投資報酬率高嗎\",\"bold\":false,\"italics\":false,\"strikethrough\":false}],\"text\":\"這種東西投資報酬率高嗎\"}"},{"id":"ChwKGkNNN3U3T1htbllFREZlRFB3Z1FkY3Q4SkpB","videoId":"5Z5uFOfWnh4","userId":"UCbaEd9B4ApB8sF_jFU15R8w","timestamp":1694271933222,"videoOffsetTimeMsec":"3859444","jsonMessage":"{\"runs\":[{\"text\":\"拿著逗貓棒ㄉ芋頭ㄟㄟ\",\"bold\":false,\"italics\":false,\"strikethrough\":false}],\"text\":\"拿著逗貓棒ㄉ芋頭ㄟㄟ\"}"},{"id":"ChwKGkNJM2IycG1LcFlFREZUclF3Z1FkR3gwQ2VR","videoId":"bUsLuI6miqg","userId":"UCbaEd9B4ApB8sF_jFU15R8w","timestamp":1694521955393,"videoOffsetTimeMsec":"1275916","jsonMessage":"{\"runs\":[{\"text\":\"芋頭安安\",\"bold\":false,\"italics\":false,\"strikethrough\":false},{\"text\":\"UC2ZWggon1NOT2TGaVUMzY7A/BtoDYovJLqiE_9EPw52guAg\",\"emoji\":{\"emoji_id\":\"UC2ZWggon1NOT2TGaVUMzY7A/BtoDYovJLqiE_9EPw52guAg\",\"shortcuts\":[\":_庫愛愛:\",\":庫愛愛:\"],\"search_terms\":[\"_庫愛愛\",\"庫愛愛\"],\"image\":[{\"url\":\"https://yt3.ggpht.com/fBvRSl4Bz_60RDtFngE1lJSqMZAWAGHvYr-2IUFWTiDmbZ3PChe2t8SyKKH1ELuQjX8guZhvvw=w48-h48-c-k-nd\",\"width\":48,\"height\":48},{\"url\":\"https://yt3.ggpht.com/fBvRSl4Bz_60RDtFngE1lJSqMZAWAGHvYr-2IUFWTiDmbZ3PChe2t8SyKKH1ELuQjX8guZhvvw=w24-h24-c-k-nd\",\"width\":24,\"height\":24}],\"is_custom\":true}}],\"text\":\"芋頭安安UC2ZWggon1NOT2TGaVUMzY7A/BtoDYovJLqiE_9EPw52guAg\"}"},{"id":"ChwKGkNNNmRtdnFQMzRFREZjckN3Z1FkbHRBRTBB","videoId":"aKqfE0kufds","userId":"UCbaEd9B4ApB8sF_jFU15R8w","timestamp":1696516364763,"videoOffsetTimeMsec":"1947319","jsonMessage":"{\"runs\":[{\"text\":\"安安\",\"bold\":false,\"italics\":false,\"strikethrough\":false}],\"text\":\"安安\"}"},{"id":"ChwKGkNMalVncXVSMzRFREZUREN3Z1FkYU1vQ2Rn","videoId":"aKqfE0kufds","userId":"UCbaEd9B4ApB8sF_jFU15R8w","timestamp":1696516735574,"videoOffsetTimeMsec":"2318072","jsonMessage":"{\"runs\":[{\"text\":\"以前看過我國小老師灌完一罐伏特加，下節課跟沒事人一樣上課\",\"bold\":false,\"italics\":false,\"strikethrough\":false},{\"text\":\"UC2ZWggon1NOT2TGaVUMzY7A/cI8AZZCwD6SQ_9EP--ut8As\",\"emoji\":{\"emoji_id\":\"UC2ZWggon1NOT2TGaVUMzY7A/cI8AZZCwD6SQ_9EP--ut8As\",\"shortcuts\":[\":_嚇到庫:\",\":嚇到庫:\"],\"search_terms\":[\"_嚇到庫\",\"嚇到庫\"],\"image\":[{\"url\":\"https://yt3.ggpht.com/TQw2OpHbZyujTMR0CUBeZeaL5hntEaayEGQQkEL4PjxZhHENTIh5AB63ZKh3kCgnINsgAezC=w48-h48-c-k-nd\",\"width\":48,\"height\":48},{\"url\":\"https://yt3.ggpht.com/TQw2OpHbZyujTMR0CUBeZeaL5hntEaayEGQQkEL4PjxZhHENTIh5AB63ZKh3kCgnINsgAezC=w24-h24-c-k-nd\",\"width\":24,\"height\":24}],\"is_custom\":true}},{\"text\":\"UC2ZWggon1NOT2TGaVUMzY7A/cI8AZZCwD6SQ_9EP--ut8As\",\"emoji\":{\"emoji_id\":\"UC2ZWggon1NOT2TGaVUMzY7A/cI8AZZCwD6SQ_9EP--ut8As\",\"shortcuts\":[\":_嚇到庫:\",\":嚇到庫:\"],\"search_terms\":[\"_嚇到庫\",\"嚇到庫\"],\"image\":[{\"url\":\"https://yt3.ggpht.com/TQw2OpHbZyujTMR0CUBeZeaL5hntEaayEGQQkEL4PjxZhHENTIh5AB63ZKh3kCgnINsgAezC=w48-h48-c-k-nd\",\"width\":48,\"height\":48},{\"url\":\"https://yt3.ggpht.com/TQw2OpHbZyujTMR0CUBeZeaL5hntEaayEGQQkEL4PjxZhHENTIh5AB63ZKh3kCgnINsgAezC=w24-h24-c-k-nd\",\"width\":24,\"height\":24}],\"is_custom\":true}},{\"text\":\"UC2ZWggon1NOT2TGaVUMzY7A/cI8AZZCwD6SQ_9EP--ut8As\",\"emoji\":{\"emoji_id\":\"UC2ZWggon1NOT2TGaVUMzY7A/cI8AZZCwD6SQ_9EP--ut8As\",\"shortcuts\":[\":_嚇到庫:\",\":嚇到庫:\"],\"search_terms\":[\"_嚇到庫\",\"嚇到庫\"],\"image\":[{\"url\":\"https://yt3.ggpht.com/TQw2OpHbZyujTMR0CUBeZeaL5hntEaayEGQQkEL4PjxZhHENTIh5AB63ZKh3kCgnINsgAezC=w48-h48-c-k-nd\",\"width\":48,\"height\":48},{\"url\":\"https://yt3.ggpht.com/TQw2OpHbZyujTMR0CUBeZeaL5hntEaayEGQQkEL4PjxZhHENTIh5AB63ZKh3kCgnINsgAezC=w24-h24-c-k-nd\",\"width\":24,\"height\":24}],\"is_custom\":true}}],\"text\":\"以前看過我國小老師灌完一罐伏特加，下節課跟沒事人一樣上課UC2ZWggon1NOT2TGaVUMzY7A/cI8AZZCwD6SQ_9EP--ut8AsUC2ZWggon1NOT2TGaVUMzY7A/cI8AZZCwD6SQ_9EP--ut8AsUC2ZWggon1NOT2TGaVUMzY7A/cI8AZZCwD6SQ_9EP--ut8As\"}"},{"id":"ChwKGkNPdmh1Yy1SMzRFREZSX0F3Z1FkRHEwTEZn","videoId":"aKqfE0kufds","userId":"UCbaEd9B4ApB8sF_jFU15R8w","timestamp":1696516812001,"videoOffsetTimeMsec":"2394536","jsonMessage":"{\"runs\":[{\"text\":\"荔枝也會超標\",\"bold\":false,\"italics\":false,\"strikethrough\":false}],\"text\":\"荔枝也會超標\"}"},{"id":"ChwKGkNOSDM0ZXJ1OVlFREZiekN3Z1FkLUp3QWp3","videoId":"k8DV4jrjfPk","userId":"UCbaEd9B4ApB8sF_jFU15R8w","timestamp":1697297747994,"videoOffsetTimeMsec":"5709613","jsonMessage":"{\"runs\":[{\"text\":\"主播安安不是初見\",\"bold\":false,\"italics\":false,\"strikethrough\":false}],\"text\":\"主播安安不是初見\"}"},{"id":"ChwKGkNJclVzWm52OVlFREZUZlB3Z1FkejQ0R05B","videoId":"k8DV4jrjfPk","userId":"UCbaEd9B4ApB8sF_jFU15R8w","timestamp":1697297845766,"videoOffsetTimeMsec":"5807363","jsonMessage":"{\"runs\":[{\"text\":\"品客+魚\",\"bold\":false,\"italics\":false,\"strikethrough\":false}],\"text\":\"品客+魚\"}"},{"id":"ChwKGkNOWEJwc1B2OVlFREZhckF3Z1FkOHc0SHBR","videoId":"k8DV4jrjfPk","userId":"UCbaEd9B4ApB8sF_jFU15R8w","timestamp":1697297933664,"videoOffsetTimeMsec":"5895187","jsonMessage":"{\"runs\":[{\"text\":\"品客比較舒服\",\"bold\":false,\"italics\":false,\"strikethrough\":false}],\"text\":\"品客比較舒服\"}"},{"id":"ChwKGkNJUGFvTmFLbElJREZaM0N3Z1FkekNJTjVB","videoId":"35dMsmD5vSg","userId":"UCbaEd9B4ApB8sF_jFU15R8w","timestamp":1698336013326,"videoOffsetTimeMsec":"6858952","jsonMessage":"{\"runs\":[{\"text\":\"ben台危機\",\"bold\":false,\"italics\":false,\"strikethrough\":false}],\"text\":\"ben台危機\"}"},{"id":"ChwKGkNQdk05TC14MElJREZiUEN3Z1FkU2dJSTZ3","videoId":"uZgAcQepenI","userId":"UCbaEd9B4ApB8sF_jFU15R8w","timestamp":1700408019747,"videoOffsetTimeMsec":"5605369","jsonMessage":"{\"runs\":[{\"text\":\"那天kuro想起了被人類支配的恐懼\",\"bold\":false,\"italics\":false,\"strikethrough\":false}],\"text\":\"那天kuro想起了被人類支配的恐懼\"}"},{"id":"ChwKGkNONkN0ZDJ4MElJREZWbkN3Z1FkUEt3T2d3","videoId":"uZgAcQepenI","userId":"UCbaEd9B4ApB8sF_jFU15R8w","timestamp":1700408081625,"videoOffsetTimeMsec":"5667212","jsonMessage":"{\"runs\":[{\"text\":\"台主被性騷擾ㄌ\",\"bold\":false,\"italics\":false,\"strikethrough\":false}],\"text\":\"台主被性騷擾ㄌ\"}"},{"id":"ChwKGkNMMkczdjZ4MElJREZhWV9yUVlkeHFZbGhR","videoId":"uZgAcQepenI","userId":"UCbaEd9B4ApB8sF_jFU15R8w","timestamp":1700408151498,"videoOffsetTimeMsec":"5737012","jsonMessage":"{\"runs\":[{\"text\":\"真色\",\"bold\":false,\"italics\":false,\"strikethrough\":false}],\"text\":\"真色\"}"},{"id":"ChwKGkNKbjlwNWF5MElJREZUYkR3Z1FkQmM0UEp3","videoId":"uZgAcQepenI","userId":"UCbaEd9B4ApB8sF_jFU15R8w","timestamp":1700408200942,"videoOffsetTimeMsec":"5786452","jsonMessage":"{\"runs\":[{\"text\":\"ban台警告\",\"bold\":false,\"italics\":false,\"strikethrough\":false}],\"text\":\"ban台警告\"}"},{"id":"ChwKGkNLdlU3THl5MElJREZkSV9yUVlkLW04N2pn","videoId":"uZgAcQepenI","userId":"UCbaEd9B4ApB8sF_jFU15R8w","timestamp":1700408281758,"videoOffsetTimeMsec":"5867346","jsonMessage":"{\"runs\":[{\"text\":\"886\",\"bold\":false,\"italics\":false,\"strikethrough\":false}],\"text\":\"886\"}"},{"id":"ChwKGkNOWEsyWVd6MElJREZUYkR3Z1FkQmM0UEp3","videoId":"uZgAcQepenI","userId":"UCbaEd9B4ApB8sF_jFU15R8w","timestamp":1700408434539,"videoOffsetTimeMsec":"6020117","jsonMessage":"{\"runs\":[{\"text\":\"9塊9\",\"bold\":false,\"italics\":false,\"strikethrough\":false}],\"text\":\"9塊9\"}"},{"id":"ChwKGkNPcTlfcmF6MElJREZhdlJ3Z1FkSEpBQmpR","videoId":"uZgAcQepenI","userId":"UCbaEd9B4ApB8sF_jFU15R8w","timestamp":1700408537939,"videoOffsetTimeMsec":"6123405","jsonMessage":"{\"runs\":[{\"text\":\"8700000\",\"bold\":false,\"italics\":false,\"strikethrough\":false}],\"text\":\"8700000\"}"},{"id":"ChwKGkNKVEpsWlMwMElJREZWbkN3Z1FkUEt3T2d3","videoId":"uZgAcQepenI","userId":"UCbaEd9B4ApB8sF_jFU15R8w","timestamp":1700408733321,"videoOffsetTimeMsec":"6318829","jsonMessage":"{\"runs\":[{\"text\":\"感覺kuro會翻\",\"bold\":false,\"italics\":false,\"strikethrough\":false}],\"text\":\"感覺kuro會翻\"}"},{"id":"ChwKGkNMM2ptdGUwMElJREZjUEJ3Z1FkX3hnRFV3","videoId":"uZgAcQepenI","userId":"UCbaEd9B4ApB8sF_jFU15R8w","timestamp":1700408873950,"videoOffsetTimeMsec":"6459494","jsonMessage":"{\"runs\":[{\"text\":\"嘗試讓你的後空翻和前空翻有區別\",\"bold\":false,\"italics\":false,\"strikethrough\":false}],\"text\":\"嘗試讓你的後空翻和前空翻有區別\"}"},{"id":"ChwKGkNPLTY1ZXkwMElJREZjRER3Z1FkWXI0TThn","videoId":"uZgAcQepenI","userId":"UCbaEd9B4ApB8sF_jFU15R8w","timestamp":1700408919204,"videoOffsetTimeMsec":"6504741","jsonMessage":"{\"runs\":[{\"text\":\"舉門\",\"bold\":false,\"italics\":false,\"strikethrough\":false}],\"text\":\"舉門\"}"},{"id":"ChwKGkNJTzQwWmExMElJREZWbkN3Z1FkUEt3T2d3","videoId":"uZgAcQepenI","userId":"UCbaEd9B4ApB8sF_jFU15R8w","timestamp":1700409006930,"videoOffsetTimeMsec":"6592473","jsonMessage":"{\"runs\":[{\"text\":\"說的真好下次別說了\",\"bold\":false,\"italics\":false,\"strikethrough\":false}],\"text\":\"說的真好下次別說了\"}"},{"id":"ChwKGkNJUDVsTmUxMElJREZYREF3Z1FkOEdVT3ZB","videoId":"uZgAcQepenI","userId":"UCbaEd9B4ApB8sF_jFU15R8w","timestamp":1700409142258,"videoOffsetTimeMsec":"6727872","jsonMessage":"{\"runs\":[{\"text\":\"誒差5000ㄌ\",\"bold\":false,\"italics\":false,\"strikethrough\":false}],\"text\":\"誒差5000ㄌ\"}"},{"id":"ChwKGkNPYktnY0MyMElJREZldkJ3Z1FkWFBnR1dB","videoId":"uZgAcQepenI","userId":"UCbaEd9B4ApB8sF_jFU15R8w","timestamp":1700409362138,"videoOffsetTimeMsec":"6947705","jsonMessage":"{\"runs\":[{\"text\":\"讓kuro跟我們打勾勾\",\"bold\":false,\"italics\":false,\"strikethrough\":false}],\"text\":\"讓kuro跟我們打勾勾\"}"},{"id":"ChwKGkNLSzA5ZWkyMElJREZSTEV3Z1FkT3E0R1d3","videoId":"uZgAcQepenI","userId":"UCbaEd9B4ApB8sF_jFU15R8w","timestamp":1700409447919,"videoOffsetTimeMsec":"7033446","jsonMessage":"{\"runs\":[{\"text\":\"色色ㄉ\",\"bold\":false,\"italics\":false,\"strikethrough\":false}],\"text\":\"色色ㄉ\"}"},{"id":"ChwKGkNQTE0tSUczMElJREZhbkN3Z1FkX2w0UFZB","videoId":"uZgAcQepenI","userId":"UCbaEd9B4ApB8sF_jFU15R8w","timestamp":1700409500402,"videoOffsetTimeMsec":"7086019","jsonMessage":"{\"runs\":[{\"text\":\"更色了\",\"bold\":false,\"italics\":false,\"strikethrough\":false}],\"text\":\"更色了\"}"},{"id":"ChwKGkNKdVY0WmEzMElJREZlTV9yUVlkVmdjQTlB","videoId":"uZgAcQepenI","userId":"UCbaEd9B4ApB8sF_jFU15R8w","timestamp":1700409544057,"videoOffsetTimeMsec":"7129589","jsonMessage":"{\"runs\":[{\"text\":\"要畢業了嗎！\",\"bold\":false,\"italics\":false,\"strikethrough\":false}],\"text\":\"要畢業了嗎！\"}"},{"id":"ChwKGkNOVzN3YmEzMElJREZla1NyUVlkZ25NSHdB","videoId":"uZgAcQepenI","userId":"UCbaEd9B4ApB8sF_jFU15R8w","timestamp":1700409610661,"videoOffsetTimeMsec":"7196216","jsonMessage":"{\"runs\":[{\"text\":\"有很庫的味道\",\"bold\":false,\"italics\":false,\"strikethrough\":false}],\"text\":\"有很庫的味道\"}"},{"id":"ChwKGkNQX1k1ZU8zMElJREZlTV9yUVlkVmdjQTlB","videoId":"uZgAcQepenI","userId":"UCbaEd9B4ApB8sF_jFU15R8w","timestamp":1700409705640,"videoOffsetTimeMsec":"7291225","jsonMessage":"{\"runs\":[{\"text\":\"？？？？\",\"bold\":false,\"italics\":false,\"strikethrough\":false}],\"text\":\"？？？？\"}"},{"id":"ChwKGkNQaW1uX08zMElJREZhbkN3Z1FkX2w0UFZB","videoId":"uZgAcQepenI","userId":"UCbaEd9B4ApB8sF_jFU15R8w","timestamp":1700409738015,"videoOffsetTimeMsec":"7323557","jsonMessage":"{\"runs\":[{\"text\":\"性癖可以冷門但不能邪門\",\"bold\":false,\"italics\":false,\"strikethrough\":false}],\"text\":\"性癖可以冷門但不能邪門\"}"},{"id":"ChwKGkNKV2s1N1c0MElJREZUYkR3Z1FkQmM0UEp3","videoId":"uZgAcQepenI","userId":"UCbaEd9B4ApB8sF_jFU15R8w","timestamp":1700409877608,"videoOffsetTimeMsec":"7463254","jsonMessage":"{\"runs\":[{\"text\":\"虫合？？？\",\"bold\":false,\"italics\":false,\"strikethrough\":false}],\"text\":\"虫合？？？\"}"},{"id":"ChwKGkNPLTQ5OUs0MElJREZYREF3Z1FkOEdVT3ZB","videoId":"uZgAcQepenI","userId":"UCbaEd9B4ApB8sF_jFU15R8w","timestamp":1700409938690,"videoOffsetTimeMsec":"7524222","jsonMessage":"{\"runs\":[{\"text\":\"胸的肉都長到下面了\",\"bold\":false,\"italics\":false,\"strikethrough\":false}],\"text\":\"胸的肉都長到下面了\"}"},{"id":"ChwKGkNQLWJpN201MElJREZkalB3Z1FkQ1BVT0l3","videoId":"uZgAcQepenI","userId":"UCbaEd9B4ApB8sF_jFU15R8w","timestamp":1700410152924,"videoOffsetTimeMsec":"7738412","jsonMessage":"{\"runs\":[{\"text\":\"其實有馬甲線只是被肉遮住了\",\"bold\":false,\"italics\":false,\"strikethrough\":false}],\"text\":\"其實有馬甲線只是被肉遮住了\"}"},{"id":"ChwKGkNOemh4YzI1MElJREZUbkR3Z1FkSjljQzhn","videoId":"uZgAcQepenI","userId":"UCbaEd9B4ApB8sF_jFU15R8w","timestamp":1700410195821,"videoOffsetTimeMsec":"7781375","jsonMessage":"{\"runs\":[{\"text\":\"一坨肥...ㄖㄡ\",\"bold\":false,\"italics\":false,\"strikethrough\":false}],\"text\":\"一坨肥...ㄖㄡ\"}"},{"id":"ChwKGkNJanhodm01MElJREZaYkN3Z1FkSE5JSGxB","videoId":"uZgAcQepenI","userId":"UCbaEd9B4ApB8sF_jFU15R8w","timestamp":1700410287070,"videoOffsetTimeMsec":"7872641","jsonMessage":"{\"runs\":[{\"text\":\"感覺kuro比較壯\",\"bold\":false,\"italics\":false,\"strikethrough\":false}],\"text\":\"感覺kuro比較壯\"}"},{"id":"ChwKGkNQS3B6cGU2MElJREZYZ1RyUVlkMlpvTmpR","videoId":"uZgAcQepenI","userId":"UCbaEd9B4ApB8sF_jFU15R8w","timestamp":1700410351157,"videoOffsetTimeMsec":"7936743","jsonMessage":"{\"runs\":[{\"text\":\"2000讚ㄌ\",\"bold\":false,\"italics\":false,\"strikethrough\":false}],\"text\":\"2000讚ㄌ\"}"},{"id":"ChwKGkNPYkt0S2k2MElJREZlTV9yUVlkVmdjQTlB","videoId":"uZgAcQepenI","userId":"UCbaEd9B4ApB8sF_jFU15R8w","timestamp":1700410386384,"videoOffsetTimeMsec":"7971918","jsonMessage":"{\"runs\":[{\"text\":\"2000讚達成\",\"bold\":false,\"italics\":false,\"strikethrough\":false}],\"text\":\"2000讚達成\"}"},{"id":"ChwKGkNMR3A3OE82MElJREZYREF3Z1FkOEdVT3ZB","videoId":"uZgAcQepenI","userId":"UCbaEd9B4ApB8sF_jFU15R8w","timestamp":1700410443970,"videoOffsetTimeMsec":"8029546","jsonMessage":"{\"runs\":[{\"text\":\"？？？？？？\",\"bold\":false,\"italics\":false,\"strikethrough\":false}],\"text\":\"？？？？？？\"}"},{"id":"ChwKGkNLaW5uTlM2MElJREZhdlJ3Z1FkSEpBQmpR","videoId":"uZgAcQepenI","userId":"UCbaEd9B4ApB8sF_jFU15R8w","timestamp":1700410478263,"videoOffsetTimeMsec":"8063785","jsonMessage":"{\"runs\":[{\"text\":\"醉了\",\"bold\":false,\"italics\":false,\"strikethrough\":false}],\"text\":\"醉了\"}"},{"id":"ChwKGkNPQ2ZoTnk2MElJREZYZ1RyUVlkMlpvTmpR","videoId":"uZgAcQepenI","userId":"UCbaEd9B4ApB8sF_jFU15R8w","timestamp":1700410494642,"videoOffsetTimeMsec":"8080127","jsonMessage":"{\"runs\":[{\"text\":\"有但不多\",\"bold\":false,\"italics\":false,\"strikethrough\":false}],\"text\":\"有但不多\"}"},{"id":"ChwKGkNNdkI2X0s2MElJREZjRER3Z1FkWXI0TThn","videoId":"uZgAcQepenI","userId":"UCbaEd9B4ApB8sF_jFU15R8w","timestamp":1700410542480,"videoOffsetTimeMsec":"8127959","jsonMessage":"{\"runs\":[{\"text\":\"怎麼說背有奶？？？\",\"bold\":false,\"italics\":false,\"strikethrough\":false}],\"text\":\"怎麼說背有奶？？？\"}"},{"id":"ChwKGkNPS1p5ZGU3MElJREZUYkR3Z1FkQmM0UEp3","videoId":"uZgAcQepenI","userId":"UCbaEd9B4ApB8sF_jFU15R8w","timestamp":1700410753729,"videoOffsetTimeMsec":"8339285","jsonMessage":"{\"runs\":[{\"text\":\"打ㄋㄚˇ會打到胸骨不建議\",\"bold\":false,\"italics\":false,\"strikethrough\":false}],\"text\":\"打ㄋㄚˇ會打到胸骨不建議\"}"},{"id":"ChwKGkNNckotSXE4MElJREZYREF3Z1FkOEdVT3ZB","videoId":"uZgAcQepenI","userId":"UCbaEd9B4ApB8sF_jFU15R8w","timestamp":1700410861453,"videoOffsetTimeMsec":"8447046","jsonMessage":"{\"runs\":[{\"text\":\"牛牛\",\"bold\":false,\"italics\":false,\"strikethrough\":false}],\"text\":\"牛牛\"}"},{"id":"ChwKGkNNeTkxTU84MElJREZlTV9yUVlkVmdjQTlB","videoId":"uZgAcQepenI","userId":"UCbaEd9B4ApB8sF_jFU15R8w","timestamp":1700410980404,"videoOffsetTimeMsec":"8565993","jsonMessage":"{\"runs\":[{\"text\":\"去沙灘角落\",\"bold\":false,\"italics\":false,\"strikethrough\":false}],\"text\":\"去沙灘角落\"}"},{"id":"ChwKGkNOcnFvT2E4MElJREZYREF3Z1FkOEdVT3ZB","videoId":"uZgAcQepenI","userId":"UCbaEd9B4ApB8sF_jFU15R8w","timestamp":1700411052959,"videoOffsetTimeMsec":"8638496","jsonMessage":"{\"runs\":[{\"text\":\"謝謝幽浮大大\",\"bold\":false,\"italics\":false,\"strikethrough\":false}],\"text\":\"謝謝幽浮大大\"}"},{"id":"ChwKGkNMU0pub3E5MElJREZSTEV3Z1FkT3E0R1d3","videoId":"uZgAcQepenI","userId":"UCbaEd9B4ApB8sF_jFU15R8w","timestamp":1700411128406,"videoOffsetTimeMsec":"8713964","jsonMessage":"{\"runs\":[{\"text\":\"晚安完直接沙啞\",\"bold\":false,\"italics\":false,\"strikethrough\":false},{\"text\":\"UC2ZWggon1NOT2TGaVUMzY7A/BtoDYtLHLqiE_9EPw52guAg\",\"emoji\":{\"emoji_id\":\"UC2ZWggon1NOT2TGaVUMzY7A/BtoDYtLHLqiE_9EPw52guAg\",\"shortcuts\":[\":_痾痾痾:\",\":痾痾痾:\"],\"search_terms\":[\"_痾痾痾\",\"痾痾痾\"],\"image\":[{\"url\":\"https://yt3.ggpht.com/3IJnY84cNgD7wwTH49u0tXwNoi9RIDLjGeA-e1DSImOnOMkTkJ38Z5CKx_-U038WYagfPd-kkA=w48-h48-c-k-nd\",\"width\":48,\"height\":48},{\"url\":\"https://yt3.ggpht.com/3IJnY84cNgD7wwTH49u0tXwNoi9RIDLjGeA-e1DSImOnOMkTkJ38Z5CKx_-U038WYagfPd-kkA=w24-h24-c-k-nd\",\"width\":24,\"height\":24}],\"is_custom\":true}}],\"text\":\"晚安完直接沙啞UC2ZWggon1NOT2TGaVUMzY7A/BtoDYtLHLqiE_9EPw52guAg\"}"},{"id":"ChwKGkNLR2wwOEc5MElJREZkalB3Z1FkQ1BVT0l3","videoId":"uZgAcQepenI","userId":"UCbaEd9B4ApB8sF_jFU15R8w","timestamp":1700411244650,"videoOffsetTimeMsec":"8830217","jsonMessage":"{\"runs\":[{\"text\":\"晚安R今天太庫辣\",\"bold\":false,\"italics\":false,\"strikethrough\":false},{\"text\":\"UC2ZWggon1NOT2TGaVUMzY7A/i4gsY7GAFIa7gwOvwYXQDw\",\"emoji\":{\"emoji_id\":\"UC2ZWggon1NOT2TGaVUMzY7A/i4gsY7GAFIa7gwOvwYXQDw\",\"shortcuts\":[\":_HII:\",\":HII:\"],\"search_terms\":[\"_HII\",\"HII\"],\"image\":[{\"url\":\"https://yt3.ggpht.com/O_NLB0L5ERYEUmP5tk8mbtN8d1-jDfCc1lKhxBj6XA_XxDeJwTHOjKkkZFxZSQtn2jFWGqvzBw=w48-h48-c-k-nd\",\"width\":48,\"height\":48},{\"url\":\"https://yt3.ggpht.com/O_NLB0L5ERYEUmP5tk8mbtN8d1-jDfCc1lKhxBj6XA_XxDeJwTHOjKkkZFxZSQtn2jFWGqvzBw=w24-h24-c-k-nd\",\"width\":24,\"height\":24}],\"is_custom\":true}},{\"text\":\"UC2ZWggon1NOT2TGaVUMzY7A/i4gsY7GAFIa7gwOvwYXQDw\",\"emoji\":{\"emoji_id\":\"UC2ZWggon1NOT2TGaVUMzY7A/i4gsY7GAFIa7gwOvwYXQDw\",\"shortcuts\":[\":_HII:\",\":HII:\"],\"search_terms\":[\"_HII\",\"HII\"],\"image\":[{\"url\":\"https://yt3.ggpht.com/O_NLB0L5ERYEUmP5tk8mbtN8d1-jDfCc1lKhxBj6XA_XxDeJwTHOjKkkZFxZSQtn2jFWGqvzBw=w48-h48-c-k-nd\",\"width\":48,\"height\":48},{\"url\":\"https://yt3.ggpht.com/O_NLB0L5ERYEUmP5tk8mbtN8d1-jDfCc1lKhxBj6XA_XxDeJwTHOjKkkZFxZSQtn2jFWGqvzBw=w24-h24-c-k-nd\",\"width\":24,\"height\":24}],\"is_custom\":true}},{\"text\":\"UC2ZWggon1NOT2TGaVUMzY7A/i4gsY7GAFIa7gwOvwYXQDw\",\"emoji\":{\"emoji_id\":\"UC2ZWggon1NOT2TGaVUMzY7A/i4gsY7GAFIa7gwOvwYXQDw\",\"shortcuts\":[\":_HII:\",\":HII:\"],\"search_terms\":[\"_HII\",\"HII\"],\"image\":[{\"url\":\"https://yt3.ggpht.com/O_NLB0L5ERYEUmP5tk8mbtN8d1-jDfCc1lKhxBj6XA_XxDeJwTHOjKkkZFxZSQtn2jFWGqvzBw=w48-h48-c-k-nd\",\"width\":48,\"height\":48},{\"url\":\"https://yt3.ggpht.com/O_NLB0L5ERYEUmP5tk8mbtN8d1-jDfCc1lKhxBj6XA_XxDeJwTHOjKkkZFxZSQtn2jFWGqvzBw=w24-h24-c-k-nd\",\"width\":24,\"height\":24}],\"is_custom\":true}}],\"text\":\"晚安R今天太庫辣UC2ZWggon1NOT2TGaVUMzY7A/i4gsY7GAFIa7gwOvwYXQDwUC2ZWggon1NOT2TGaVUMzY7A/i4gsY7GAFIa7gwOvwYXQDwUC2ZWggon1NOT2TGaVUMzY7A/i4gsY7GAFIa7gwOvwYXQDw\"}"},{"id":"ChwKGkNMN0NsdTNpLUlJREZhWEV3Z1FkLVA0SWx3","videoId":"FNNbXuX0W0U","userId":"UCbaEd9B4ApB8sF_jFU15R8w","timestamp":1701795657550,"videoOffsetTimeMsec":"10789122","jsonMessage":"{\"runs\":[{\"text\":\"剛進來...\",\"bold\":false,\"italics\":false,\"strikethrough\":false},{\"text\":\"□\",\"bold\":false,\"italics\":false,\"strikethrough\":false},{\"text\":\"□\",\"bold\":false,\"italics\":false,\"strikethrough\":false},{\"text\":\"□\",\"bold\":false,\"italics\":false,\"strikethrough\":false}],\"text\":\"剛進來...□□□\"}"},{"id":"ChwKGkNNaXE4T1R3aklNREZhZlF3Z1FkZFFrRXZB","videoId":"_kFRLj0KXok","userId":"UCbaEd9B4ApB8sF_jFU15R8w","timestamp":1702486593015,"videoOffsetTimeMsec":"10582515","jsonMessage":"{\"runs\":[{\"text\":\"感覺庫庫騎檔車在路上99%會被攔撿\",\"bold\":false,\"italics\":false,\"strikethrough\":false},{\"text\":\"UC2ZWggon1NOT2TGaVUMzY7A/YQheZf6ZGqyQ_9EPq_28mAI\",\"emoji\":{\"emoji_id\":\"UC2ZWggon1NOT2TGaVUMzY7A/YQheZf6ZGqyQ_9EPq_28mAI\",\"shortcuts\":[\":_笑死ㄝ:\",\":笑死ㄝ:\"],\"search_terms\":[\"_笑死ㄝ\",\"笑死ㄝ\"],\"image\":[{\"url\":\"https://yt3.ggpht.com/GNr399KBQCMpXO2_w8R6H1hlFrBr6G1w3YClBpCH3xcP3Nqz-U83CDE55ZPP288FRSbhCqCiC2o=w48-h48-c-k-nd\",\"width\":48,\"height\":48},{\"url\":\"https://yt3.ggpht.com/GNr399KBQCMpXO2_w8R6H1hlFrBr6G1w3YClBpCH3xcP3Nqz-U83CDE55ZPP288FRSbhCqCiC2o=w24-h24-c-k-nd\",\"width\":24,\"height\":24}],\"is_custom\":true}}],\"text\":\"感覺庫庫騎檔車在路上99%會被攔撿UC2ZWggon1NOT2TGaVUMzY7A/YQheZf6ZGqyQ_9EPq_28mAI\"}"},{"id":"ChwKGkNMUE52cER4aklNREZUX0R3Z1FkbzVvR0Rn","videoId":"_kFRLj0KXok","userId":"UCbaEd9B4ApB8sF_jFU15R8w","timestamp":1702486684468,"videoOffsetTimeMsec":"10673934","jsonMessage":"{\"runs\":[{\"text\":\"庫庫的身高真的騎的到檔車ㄇ\",\"bold\":false,\"italics\":false,\"strikethrough\":false},{\"text\":\"UC2ZWggon1NOT2TGaVUMzY7A/8YZjZMTaKqaJ_9EPk9-E6AI\",\"emoji\":{\"emoji_id\":\"UC2ZWggon1NOT2TGaVUMzY7A/8YZjZMTaKqaJ_9EPk9-E6AI\",\"shortcuts\":[\":_問號問號:\",\":問號問號:\"],\"search_terms\":[\"_問號問號\",\"問號問號\"],\"image\":[{\"url\":\"https://yt3.ggpht.com/-LjglKBzEFJ1ySZIw8bgDW1xlsK8KnuWIFHzFdnNzh0OywmTqXuzjUV4IeXyZPIgyRT2KjGcng=w48-h48-c-k-nd\",\"width\":48,\"height\":48},{\"url\":\"https://yt3.ggpht.com/-LjglKBzEFJ1ySZIw8bgDW1xlsK8KnuWIFHzFdnNzh0OywmTqXuzjUV4IeXyZPIgyRT2KjGcng=w24-h24-c-k-nd\",\"width\":24,\"height\":24}],\"is_custom\":true}},{\"text\":\"UC2ZWggon1NOT2TGaVUMzY7A/8YZjZMTaKqaJ_9EPk9-E6AI\",\"emoji\":{\"emoji_id\":\"UC2ZWggon1NOT2TGaVUMzY7A/8YZjZMTaKqaJ_9EPk9-E6AI\",\"shortcuts\":[\":_問號問號:\",\":問號問號:\"],\"search_terms\":[\"_問號問號\",\"問號問號\"],\"image\":[{\"url\":\"https://yt3.ggpht.com/-LjglKBzEFJ1ySZIw8bgDW1xlsK8KnuWIFHzFdnNzh0OywmTqXuzjUV4IeXyZPIgyRT2KjGcng=w48-h48-c-k-nd\",\"width\":48,\"height\":48},{\"url\":\"https://yt3.ggpht.com/-LjglKBzEFJ1ySZIw8bgDW1xlsK8KnuWIFHzFdnNzh0OywmTqXuzjUV4IeXyZPIgyRT2KjGcng=w24-h24-c-k-nd\",\"width\":24,\"height\":24}],\"is_custom\":true}},{\"text\":\"UC2ZWggon1NOT2TGaVUMzY7A/8YZjZMTaKqaJ_9EPk9-E6AI\",\"emoji\":{\"emoji_id\":\"UC2ZWggon1NOT2TGaVUMzY7A/8YZjZMTaKqaJ_9EPk9-E6AI\",\"shortcuts\":[\":_問號問號:\",\":問號問號:\"],\"search_terms\":[\"_問號問號\",\"問號問號\"],\"image\":[{\"url\":\"https://yt3.ggpht.com/-LjglKBzEFJ1ySZIw8bgDW1xlsK8KnuWIFHzFdnNzh0OywmTqXuzjUV4IeXyZPIgyRT2KjGcng=w48-h48-c-k-nd\",\"width\":48,\"height\":48},{\"url\":\"https://yt3.ggpht.com/-LjglKBzEFJ1ySZIw8bgDW1xlsK8KnuWIFHzFdnNzh0OywmTqXuzjUV4IeXyZPIgyRT2KjGcng=w24-h24-c-k-nd\",\"width\":24,\"height\":24}],\"is_custom\":true}}],\"text\":\"庫庫的身高真的騎的到檔車ㄇUC2ZWggon1NOT2TGaVUMzY7A/8YZjZMTaKqaJ_9EPk9-E6AIUC2ZWggon1NOT2TGaVUMzY7A/8YZjZMTaKqaJ_9EPk9-E6AIUC2ZWggon1NOT2TGaVUMzY7A/8YZjZMTaKqaJ_9EPk9-E6AI\"}"},{"id":"ChwKGkNPVG93ckh4aklNREZUclB3Z1FkZHMwT1Fn","videoId":"_kFRLj0KXok","userId":"UCbaEd9B4ApB8sF_jFU15R8w","timestamp":1702486753743,"videoOffsetTimeMsec":"10743167","jsonMessage":"{\"runs\":[{\"text\":\"晚安881\",\"bold\":false,\"italics\":false,\"strikethrough\":false},{\"text\":\"□\",\"bold\":false,\"italics\":false,\"strikethrough\":false},{\"text\":\"□\",\"bold\":false,\"italics\":false,\"strikethrough\":false},{\"text\":\"□\",\"bold\":false,\"italics\":false,\"strikethrough\":false}],\"text\":\"晚安881□□□\"}"},{"id":"ChwKGkNQS3VqN3VpOW9NREZkX0J3Z1FkWENZSnlB","videoId":"vFiLRm0t_Jk","userId":"UCbaEd9B4ApB8sF_jFU15R8w","timestamp":1706107699733,"videoOffsetTimeMsec":"2831429","jsonMessage":"{\"runs\":[{\"text\":\"感覺庫庫的本子就很棒\",\"bold\":false,\"italics\":false,\"strikethrough\":false}],\"text\":\"感覺庫庫的本子就很棒\"}"},{"id":"ChwKGkNQbkNxY3ZDc0lZREZTN0F3Z1FkLUJRTTVR","videoId":"Py1xFk4DNyA","userId":"UCbaEd9B4ApB8sF_jFU15R8w","timestamp":1716905281496,"videoOffsetTimeMsec":"363126","jsonMessage":"{\"runs\":[{\"text\":\"安安啊庫庫剛動完手術來看你\",\"bold\":false,\"italics\":false,\"strikethrough\":false}],\"text\":\"安安啊庫庫剛動完手術來看你\"}"},{"id":"ChwKGkNKcjZ5OVBGc0lZREZRZkN3Z1Fka3V3UFJR","videoId":"Py1xFk4DNyA","userId":"UCbaEd9B4ApB8sF_jFU15R8w","timestamp":1716906104144,"videoOffsetTimeMsec":"1185715","jsonMessage":"{\"runs\":[{\"text\":\"左抱抱龍又跳跳虎勒\",\"bold\":false,\"italics\":false,\"strikethrough\":false}],\"text\":\"左抱抱龍又跳跳虎勒\"}"},{"id":"ChwKGkNQaVhnc3ZHc0lZREZYWEx3Z1FkRkc4UGNn","videoId":"Py1xFk4DNyA","userId":"UCbaEd9B4ApB8sF_jFU15R8w","timestamp":1716906354592,"videoOffsetTimeMsec":"1436205","jsonMessage":"{\"runs\":[{\"text\":\"庫庫會用日文罵ㄍㄋㄋ嗎\",\"bold\":false,\"italics\":false,\"strikethrough\":false}],\"text\":\"庫庫會用日文罵ㄍㄋㄋ嗎\"}"},{"id":"ChwKGkNNU2U4cGZIc0lZREZVVEJ3Z1FkdndnT0Rn","videoId":"Py1xFk4DNyA","userId":"UCbaEd9B4ApB8sF_jFU15R8w","timestamp":1716906515813,"videoOffsetTimeMsec":"1597494","jsonMessage":"{\"runs\":[{\"text\":\"北車外面的不用錢還有冷風可以吹\",\"bold\":false,\"italics\":false,\"strikethrough\":false}],\"text\":\"北車外面的不用錢還有冷風可以吹\"}"},{"id":"ChwKGkNKYlZ5ZGJIc0lZREZmN0V3Z1Fkbll3RkRR","videoId":"Py1xFk4DNyA","userId":"UCbaEd9B4ApB8sF_jFU15R8w","timestamp":1716906647270,"videoOffsetTimeMsec":"1728855","jsonMessage":"{\"runs\":[{\"text\":\"腋來香\",\"bold\":false,\"italics\":false,\"strikethrough\":false}],\"text\":\"腋來香\"}"}]