[{"id":"ChwKGkNQeVZuOVdmMElJREZSTEV3Z1FkT3E0R1d3","videoId":"uZgAcQepenI","userId":"UCjjPTEQ7cFTXTqNoDHCKy4Q","timestamp":1700403232651,"videoOffsetTimeMsec":"818234","jsonMessage":"{\"runs\":[{\"text\":\"安安~~~\",\"bold\":false,\"italics\":false,\"strikethrough\":false}],\"text\":\"安安~~~\"}"},{"id":"ChwKGkNNMlVvOWU2MElJREZla1NyUVlkZ25NSHdB","videoId":"uZgAcQepenI","userId":"UCjjPTEQ7cFTXTqNoDHCKy4Q","timestamp":1700410484662,"videoOffsetTimeMsec":"8070170","jsonMessage":"{\"runs\":[{\"text\":\"泰庫啦~\",\"bold\":false,\"italics\":false,\"strikethrough\":false}],\"text\":\"泰庫啦~\"}"}]