[{"id":"ChwKGkNOblA2dktqd29jREZaekR3Z1FkdENNUDBR","videoId":"sid-hDYHkm8","userId":"UCHRIFv4opou_WA7C7LldthA","timestamp":1721913564652,"videoOffsetTimeMsec":"895169","jsonMessage":"{\"runs\":[{\"text\":\"安安\",\"bold\":false,\"italics\":false,\"strikethrough\":false}],\"text\":\"安安\"}"},{"id":"ChwKGkNQM2s3c0Q5em9jREZZclB3Z1Fkck00aDFR","videoId":"M-JqLtjZjFw","userId":"UCHRIFv4opou_WA7C7LldthA","timestamp":1722349935922,"videoOffsetTimeMsec":"1804446","jsonMessage":"{\"runs\":[{\"text\":\"安安\",\"bold\":false,\"italics\":false,\"strikethrough\":false}],\"text\":\"安安\"}"},{"id":"ChwKGkNNenIwWXI5cTRnREZkYkh3Z1FkU1Q4RUVB","videoId":"H9q_w4fNG0o","userId":"UCHRIFv4opou_WA7C7LldthA","timestamp":1725545277849,"videoOffsetTimeMsec":"371482","jsonMessage":"{\"runs\":[{\"text\":\"UCkszU2WH9gy1mb0dV-11UJg/ssIfY7OFG5OykQOpn4CQCw\",\"emoji\":{\"emoji_id\":\"UCkszU2WH9gy1mb0dV-11UJg/ssIfY7OFG5OykQOpn4CQCw\",\"shortcuts\":[\":person-turqouise-waving:\"],\"search_terms\":[\"person-turqouise-waving\"],\"image\":[{\"url\":\"https://yt3.ggpht.com/uNSzQ2M106OC1L3VGzrOsGNjopboOv-m1bnZKFGuh0DxcceSpYHhYbuyggcgnYyaF3o-AQ=w48-h48-c-k-nd\",\"width\":48,\"height\":48},{\"url\":\"https://yt3.ggpht.com/uNSzQ2M106OC1L3VGzrOsGNjopboOv-m1bnZKFGuh0DxcceSpYHhYbuyggcgnYyaF3o-AQ=w24-h24-c-k-nd\",\"width\":24,\"height\":24}],\"is_custom\":true}}],\"text\":\"UCkszU2WH9gy1mb0dV-11UJg/ssIfY7OFG5OykQOpn4CQCw\"}"}]