[{"id":"ChwKGkNMU0JrbzNVcUlRREZjVTIxZ0FkanVNRDJn","videoId":"jSgHWD6ahzk","userId":"UCbesQM8jQj0rLt0zDsNjadQ","timestampUsec":"1707839012052652","videoOffsetTimeMsec":"5945511","jsonMessage":"{\"runs\":[{\"text\":\"was gifted a membership by \",\"bold\":false,\"italics\":true,\"strikethrough\":false},{\"text\":\"エピック[殞幽]\",\"bold\":true,\"italics\":true,\"strikethrough\":false}],\"text\":\"was gifted a membership by エピック[殞幽]\"}"},{"id":"ChwKGkNLYTNsY1RqdW9ZREZlVVAxZ0FkX2pRT3lR","videoId":"5idMFtCngfo","userId":"UCbesQM8jQj0rLt0zDsNjadQ","timestampUsec":"1717257722295957","videoOffsetTimeMsec":"7214711","jsonMessage":"{\"runs\":[{\"text\":\"was gifted a membership by \",\"bold\":false,\"italics\":true,\"strikethrough\":false},{\"text\":\"6n0\",\"bold\":true,\"italics\":true,\"strikethrough\":false}],\"text\":\"was gifted a membership by 6n0\"}"},{"id":"ChwKGkNKejJoN3pkcTRjREZhQUgxZ0FkTC1jRUtn","videoId":"XrVxjhmMvjs","userId":"UCbesQM8jQj0rLt0zDsNjadQ","timestampUsec":"1721138745086583","videoOffsetTimeMsec":"227859","jsonMessage":"{\"runs\":[{\"text\":\"was gifted a membership by \",\"bold\":false,\"italics\":true,\"strikethrough\":false},{\"text\":\"エピック[殞幽]\",\"bold\":true,\"italics\":true,\"strikethrough\":false}],\"text\":\"was gifted a membership by エピック[殞幽]\"}"}]