[{"id":"ChwKGkNPbUV6N1NmaElvREZYRFF3Z1FkZHI0QUtn","videoId":"el7qq0Xcn0M","userId":"UCw0_dRLl8jdkDhYsbtVgQIA","timestamp":1732976196184,"videoOffsetTimeMsec":"849830","jsonMessage":"{\"runs\":[{\"text\":\"安安\",\"bold\":false,\"italics\":false,\"strikethrough\":false}],\"text\":\"安安\"}"},{"id":"ChwKGkNOYjhsTHFuaElvREZkTVdyUVlkS1VRZ19B","videoId":"el7qq0Xcn0M","userId":"UCw0_dRLl8jdkDhYsbtVgQIA","timestamp":1732978355291,"videoOffsetTimeMsec":"3008892","jsonMessage":"{\"runs\":[{\"text\":\"UC2ZWggon1NOT2TGaVUMzY7A/BtoDYtLHLqiE_9EPw52guAg\",\"emoji\":{\"emoji_id\":\"UC2ZWggon1NOT2TGaVUMzY7A/BtoDYtLHLqiE_9EPw52guAg\",\"shortcuts\":[\":_痾痾痾:\",\":痾痾痾:\"],\"search_terms\":[\"_痾痾痾\",\"痾痾痾\"],\"image\":[{\"url\":\"https://yt3.ggpht.com/3IJnY84cNgD7wwTH49u0tXwNoi9RIDLjGeA-e1DSImOnOMkTkJ38Z5CKx_-U038WYagfPd-kkA=w48-h48-c-k-nd\",\"width\":48,\"height\":48},{\"url\":\"https://yt3.ggpht.com/3IJnY84cNgD7wwTH49u0tXwNoi9RIDLjGeA-e1DSImOnOMkTkJ38Z5CKx_-U038WYagfPd-kkA=w24-h24-c-k-nd\",\"width\":24,\"height\":24}],\"is_custom\":true}}],\"text\":\"UC2ZWggon1NOT2TGaVUMzY7A/BtoDYtLHLqiE_9EPw52guAg\"}"},{"id":"ChwKGkNPRG54cG1waElvREZUX0N3Z1FkZG93VFpB","videoId":"el7qq0Xcn0M","userId":"UCw0_dRLl8jdkDhYsbtVgQIA","timestamp":1732978823772,"videoOffsetTimeMsec":"3477399","jsonMessage":"{\"runs\":[{\"text\":\"流血了XD\",\"bold\":false,\"italics\":false,\"strikethrough\":false}],\"text\":\"流血了XD\"}"},{"id":"ChwKGkNJbmdsN2VwaElvREZTSEF3Z1FkSVJRWVhn","videoId":"el7qq0Xcn0M","userId":"UCw0_dRLl8jdkDhYsbtVgQIA","timestamp":1732978885915,"videoOffsetTimeMsec":"3539575","jsonMessage":"{\"runs\":[{\"text\":\"我血滿的\",\"bold\":false,\"italics\":false,\"strikethrough\":false}],\"text\":\"我血滿的\"}"},{"id":"ChwKGkNLblB4X0twaElvREZUSV9yUVlkOFhvWV9n","videoId":"el7qq0Xcn0M","userId":"UCw0_dRLl8jdkDhYsbtVgQIA","timestamp":1732979010434,"videoOffsetTimeMsec":"3664065","jsonMessage":"{\"runs\":[{\"text\":\"懂得都懂\",\"bold\":false,\"italics\":false,\"strikethrough\":false}],\"text\":\"懂得都懂\"}"}]